{"791cb8694ce9e6065312e7390415639d":{"__packager_asset":true,"fileSystemLocation":"C:\\Users\\alejo\\Desktop\\SportsMatch\\sportsmatch\\client\\assets","httpServerLocation":"/assets/assets","width":202,"height":258,"scales":[1],"files":["C:\\Users\\alejo\\Desktop\\SportsMatch\\sportsmatch\\client\\assets\\logo-uem21removebgpreview-11.png"],"hash":"791cb8694ce9e6065312e7390415639d","name":"logo-uem21removebgpreview-11","type":"png","fileHashes":["791cb8694ce9e6065312e7390415639d"]},"68ac7399b90dc8fca9b478812550ba5c":{"__packager_asset":true,"fileSystemLocation":"C:\\Users\\alejo\\Desktop\\SportsMatch\\sportsmatch\\client\\assets","httpServerLocation":"/assets/assets","width":135,"height":135,"scales":[1],"files":["C:\\Users\\alejo\\Desktop\\SportsMatch\\sportsmatch\\client\\assets\\mask-group8.png"],"hash":"68ac7399b90dc8fca9b478812550ba5c","name":"mask-group8","type":"png","fileHashes":["68ac7399b90dc8fca9b478812550ba5c"]},"fbd57a88a3b9404430cec25507fc1e5f":{"__packager_asset":true,"fileSystemLocation":"C:\\Users\\alejo\\Desktop\\SportsMatch\\sportsmatch\\client\\assets","httpServerLocation":"/assets/assets","width":3257,"height":1245,"scales":[1],"files":["C:\\Users\\alejo\\Desktop\\SportsMatch\\sportsmatch\\client\\assets\\fondo-inicial.png"],"hash":"fbd57a88a3b9404430cec25507fc1e5f","name":"fondo-inicial","type":"png","fileHashes":["fbd57a88a3b9404430cec25507fc1e5f"]},"74b4284fbd23fb369cbd4ce575e88573":{"__packager_asset":true,"fileSystemLocation":"C:\\Users\\alejo\\Desktop\\SportsMatch\\sportsmatch\\client\\assets","httpServerLocation":"/assets/assets","width":516,"height":122,"scales":[1],"files":["C:\\Users\\alejo\\Desktop\\SportsMatch\\sportsmatch\\client\\assets\\group-1.png"],"hash":"74b4284fbd23fb369cbd4ce575e88573","name":"group-1","type":"png","fileHashes":["74b4284fbd23fb369cbd4ce575e88573"]},"8192e457faaa6ad8dc5b6730c7e761fe":{"__packager_asset":true,"fileSystemLocation":"C:\\Users\\alejo\\Desktop\\SportsMatch\\sportsmatch\\client\\assets","httpServerLocation":"/assets/assets","width":58,"height":60,"scales":[1],"files":["C:\\Users\\alejo\\Desktop\\SportsMatch\\sportsmatch\\client\\assets\\group-236.png"],"hash":"8192e457faaa6ad8dc5b6730c7e761fe","name":"group-236","type":"png","fileHashes":["8192e457faaa6ad8dc5b6730c7e761fe"]},"9aa3cf9e47afb9db2213f6c6cbd29991":{"__packager_asset":true,"fileSystemLocation":"C:\\Users\\alejo\\Desktop\\SportsMatch\\sportsmatch\\client\\assets","httpServerLocation":"/assets/assets","width":57,"height":69,"scales":[1],"files":["C:\\Users\\alejo\\Desktop\\SportsMatch\\sportsmatch\\client\\assets\\group-237.png"],"hash":"9aa3cf9e47afb9db2213f6c6cbd29991","name":"group-237","type":"png","fileHashes":["9aa3cf9e47afb9db2213f6c6cbd29991"]},"7529acfbc1b1360afcd718434e928f75":{"__packager_asset":true,"fileSystemLocation":"C:\\Users\\alejo\\Desktop\\SportsMatch\\sportsmatch\\client\\assets","httpServerLocation":"/assets/assets","width":67,"height":66,"scales":[1],"files":["C:\\Users\\alejo\\Desktop\\SportsMatch\\sportsmatch\\client\\assets\\group12.png"],"hash":"7529acfbc1b1360afcd718434e928f75","name":"group12","type":"png","fileHashes":["7529acfbc1b1360afcd718434e928f75"]},"ff66d8e739b39245a38ec4a578b4ea1d":{"__packager_asset":true,"fileSystemLocation":"C:\\Users\\alejo\\Desktop\\SportsMatch\\sportsmatch\\client\\assets","httpServerLocation":"/assets/assets","width":65,"height":48,"scales":[1],"files":["C:\\Users\\alejo\\Desktop\\SportsMatch\\sportsmatch\\client\\assets\\group-238.png"],"hash":"ff66d8e739b39245a38ec4a578b4ea1d","name":"group-238","type":"png","fileHashes":["ff66d8e739b39245a38ec4a578b4ea1d"]},"e60d44dbdc7b840523f1bf21fcdf9d12":{"__packager_asset":true,"fileSystemLocation":"C:\\Users\\alejo\\Desktop\\SportsMatch\\sportsmatch\\client\\assets","httpServerLocation":"/assets/assets","width":407,"height":407,"scales":[1],"files":["C:\\Users\\alejo\\Desktop\\SportsMatch\\sportsmatch\\client\\assets\\grupo-futbol.png"],"hash":"e60d44dbdc7b840523f1bf21fcdf9d12","name":"grupo-futbol","type":"png","fileHashes":["e60d44dbdc7b840523f1bf21fcdf9d12"]},"99c6857e0a151aee68e8d7365c9d748a":{"__packager_asset":true,"fileSystemLocation":"C:\\Users\\alejo\\Desktop\\SportsMatch\\sportsmatch\\client\\assets","httpServerLocation":"/assets/assets","width":407,"height":407,"scales":[1],"files":["C:\\Users\\alejo\\Desktop\\SportsMatch\\sportsmatch\\client\\assets\\group-389.png"],"hash":"99c6857e0a151aee68e8d7365c9d748a","name":"group-389","type":"png","fileHashes":["99c6857e0a151aee68e8d7365c9d748a"]},"b0e95d31c2d8942de42e444b247cb3ce":{"__packager_asset":true,"fileSystemLocation":"C:\\Users\\alejo\\Desktop\\SportsMatch\\sportsmatch\\client\\assets","httpServerLocation":"/assets/assets","width":407,"height":407,"scales":[1],"files":["C:\\Users\\alejo\\Desktop\\SportsMatch\\sportsmatch\\client\\assets\\grupo-baloncesto.png"],"hash":"b0e95d31c2d8942de42e444b247cb3ce","name":"grupo-baloncesto","type":"png","fileHashes":["b0e95d31c2d8942de42e444b247cb3ce"]},"64a97190ea67b32e09a5f84cd0009e82":{"__packager_asset":true,"fileSystemLocation":"C:\\Users\\alejo\\Desktop\\SportsMatch\\sportsmatch\\client\\assets","httpServerLocation":"/assets/assets","width":407,"height":407,"scales":[1],"files":["C:\\Users\\alejo\\Desktop\\SportsMatch\\sportsmatch\\client\\assets\\group-390.png"],"hash":"64a97190ea67b32e09a5f84cd0009e82","name":"group-390","type":"png","fileHashes":["64a97190ea67b32e09a5f84cd0009e82"]},"a2236254600000e87f595c0caf28eeef":{"__packager_asset":true,"fileSystemLocation":"C:\\Users\\alejo\\Desktop\\SportsMatch\\sportsmatch\\client\\assets","httpServerLocation":"/assets/assets","width":407,"height":407,"scales":[1],"files":["C:\\Users\\alejo\\Desktop\\SportsMatch\\sportsmatch\\client\\assets\\grupo-futbol-sala.png"],"hash":"a2236254600000e87f595c0caf28eeef","name":"grupo-futbol-sala","type":"png","fileHashes":["a2236254600000e87f595c0caf28eeef"]},"383764a274088fe9a9064e8b3b247399":{"__packager_asset":true,"fileSystemLocation":"C:\\Users\\alejo\\Desktop\\SportsMatch\\sportsmatch\\client\\assets","httpServerLocation":"/assets/assets","width":407,"height":407,"scales":[1],"files":["C:\\Users\\alejo\\Desktop\\SportsMatch\\sportsmatch\\client\\assets\\group-395.png"],"hash":"383764a274088fe9a9064e8b3b247399","name":"group-395","type":"png","fileHashes":["383764a274088fe9a9064e8b3b247399"]},"80238a231504d971caa575342550307a":{"__packager_asset":true,"fileSystemLocation":"C:\\Users\\alejo\\Desktop\\SportsMatch\\sportsmatch\\client\\assets","httpServerLocation":"/assets/assets","width":407,"height":407,"scales":[1],"files":["C:\\Users\\alejo\\Desktop\\SportsMatch\\sportsmatch\\client\\assets\\grupo-hockey.png"],"hash":"80238a231504d971caa575342550307a","name":"grupo-hockey","type":"png","fileHashes":["80238a231504d971caa575342550307a"]},"69b2c7f16bf9e4d4257cb711d1eab823":{"__packager_asset":true,"fileSystemLocation":"C:\\Users\\alejo\\Desktop\\SportsMatch\\sportsmatch\\client\\assets","httpServerLocation":"/assets/assets","width":407,"height":407,"scales":[1],"files":["C:\\Users\\alejo\\Desktop\\SportsMatch\\sportsmatch\\client\\assets\\group-391.png"],"hash":"69b2c7f16bf9e4d4257cb711d1eab823","name":"group-391","type":"png","fileHashes":["69b2c7f16bf9e4d4257cb711d1eab823"]},"bba58e15677c0db7aee86e8c63b044da":{"__packager_asset":true,"fileSystemLocation":"C:\\Users\\alejo\\Desktop\\SportsMatch\\sportsmatch\\client\\assets","httpServerLocation":"/assets/assets","width":136,"height":136,"scales":[1],"files":["C:\\Users\\alejo\\Desktop\\SportsMatch\\sportsmatch\\client\\assets\\grupo-voleibol.png"],"hash":"bba58e15677c0db7aee86e8c63b044da","name":"grupo-voleibol","type":"png","fileHashes":["bba58e15677c0db7aee86e8c63b044da"]},"869e67531c3f5c3720532720034e39f6":{"__packager_asset":true,"fileSystemLocation":"C:\\Users\\alejo\\Desktop\\SportsMatch\\sportsmatch\\client\\assets","httpServerLocation":"/assets/assets","width":136,"height":136,"scales":[1],"files":["C:\\Users\\alejo\\Desktop\\SportsMatch\\sportsmatch\\client\\assets\\group-393.png"],"hash":"869e67531c3f5c3720532720034e39f6","name":"group-393","type":"png","fileHashes":["869e67531c3f5c3720532720034e39f6"]},"caac2900846dcb7205937cb1875df727":{"__packager_asset":true,"fileSystemLocation":"C:\\Users\\alejo\\Desktop\\SportsMatch\\sportsmatch\\client\\assets","httpServerLocation":"/assets/assets","width":407,"height":407,"scales":[1],"files":["C:\\Users\\alejo\\Desktop\\SportsMatch\\sportsmatch\\client\\assets\\grupo-balonmano.png"],"hash":"caac2900846dcb7205937cb1875df727","name":"grupo-balonmano","type":"png","fileHashes":["caac2900846dcb7205937cb1875df727"]},"adba5c4dc65b5c9412a08ee0ea2820cf":{"__packager_asset":true,"fileSystemLocation":"C:\\Users\\alejo\\Desktop\\SportsMatch\\sportsmatch\\client\\assets","httpServerLocation":"/assets/assets","width":407,"height":407,"scales":[1],"files":["C:\\Users\\alejo\\Desktop\\SportsMatch\\sportsmatch\\client\\assets\\group-394.png"],"hash":"adba5c4dc65b5c9412a08ee0ea2820cf","name":"group-394","type":"png","fileHashes":["adba5c4dc65b5c9412a08ee0ea2820cf"]},"05b4c01f500d7364427eed00a5710431":{"__packager_asset":true,"fileSystemLocation":"C:\\Users\\alejo\\Desktop\\SportsMatch\\sportsmatch\\client\\assets","httpServerLocation":"/assets/assets","width":36,"height":21,"scales":[1],"files":["C:\\Users\\alejo\\Desktop\\SportsMatch\\sportsmatch\\client\\assets\\coolicon2.png"],"hash":"05b4c01f500d7364427eed00a5710431","name":"coolicon2","type":"png","fileHashes":["05b4c01f500d7364427eed00a5710431"]},"610046fd5ff51e3229f38b65b707c100":{"__packager_asset":true,"fileSystemLocation":"C:\\Users\\alejo\\Desktop\\SportsMatch\\sportsmatch\\client\\assets","httpServerLocation":"/assets/assets","width":512,"height":512,"scales":[1],"files":["C:\\Users\\alejo\\Desktop\\SportsMatch\\sportsmatch\\client\\assets\\avatarr.png"],"hash":"610046fd5ff51e3229f38b65b707c100","name":"avatarr","type":"png","fileHashes":["610046fd5ff51e3229f38b65b707c100"]},"8aec13fd5652a825dd93de05cc4e29b0":{"__packager_asset":true,"fileSystemLocation":"C:\\Users\\alejo\\Desktop\\SportsMatch\\sportsmatch\\client\\assets","httpServerLocation":"/assets/assets","width":150,"height":150,"scales":[1],"files":["C:\\Users\\alejo\\Desktop\\SportsMatch\\sportsmatch\\client\\assets\\imagePlaceholder.png"],"hash":"8aec13fd5652a825dd93de05cc4e29b0","name":"imagePlaceholder","type":"png","fileHashes":["8aec13fd5652a825dd93de05cc4e29b0"]},"9a1ada2e7b5c488b45fc4f330f2155dc":{"__packager_asset":true,"fileSystemLocation":"C:\\Users\\alejo\\Desktop\\SportsMatch\\sportsmatch\\client\\assets","httpServerLocation":"/assets/assets","width":351,"height":351,"scales":[1],"files":["C:\\Users\\alejo\\Desktop\\SportsMatch\\sportsmatch\\client\\assets\\circulo.png"],"hash":"9a1ada2e7b5c488b45fc4f330f2155dc","name":"circulo","type":"png","fileHashes":["9a1ada2e7b5c488b45fc4f330f2155dc"]},"2cb18f270ace48dead0e81f1cf1bafc8":{"__packager_asset":true,"fileSystemLocation":"C:\\Users\\alejo\\Desktop\\SportsMatch\\sportsmatch\\client\\assets","httpServerLocation":"/assets/assets","width":352,"height":440,"scales":[1],"files":["C:\\Users\\alejo\\Desktop\\SportsMatch\\sportsmatch\\client\\assets\\hannahredingkqyboqrw5wunsplash-1.png"],"hash":"2cb18f270ace48dead0e81f1cf1bafc8","name":"hannahredingkqyboqrw5wunsplash-1","type":"png","fileHashes":["2cb18f270ace48dead0e81f1cf1bafc8"]},"bbb3a7e62115901929009a44e377e7cf":{"__packager_asset":true,"fileSystemLocation":"C:\\Users\\alejo\\Desktop\\SportsMatch\\sportsmatch\\client\\assets","httpServerLocation":"/assets/assets","width":352,"height":440,"scales":[1],"files":["C:\\Users\\alejo\\Desktop\\SportsMatch\\sportsmatch\\client\\assets\\hannahredingkqyboqrw5wunsplash-2.png"],"hash":"bbb3a7e62115901929009a44e377e7cf","name":"hannahredingkqyboqrw5wunsplash-2","type":"png","fileHashes":["bbb3a7e62115901929009a44e377e7cf"]},"cbc3db4d0d1b488f72e71b2a5b249bff":{"__packager_asset":true,"fileSystemLocation":"C:\\Users\\alejo\\Desktop\\SportsMatch\\sportsmatch\\client\\assets","httpServerLocation":"/assets/assets","width":721,"height":888,"scales":[1],"files":["C:\\Users\\alejo\\Desktop\\SportsMatch\\sportsmatch\\client\\assets\\nickfithenbuugssofvounsplash-1.png"],"hash":"cbc3db4d0d1b488f72e71b2a5b249bff","name":"nickfithenbuugssofvounsplash-1","type":"png","fileHashes":["cbc3db4d0d1b488f72e71b2a5b249bff"]},"64954ec97ee5b23a0df87f0932e2bafa":{"__packager_asset":true,"fileSystemLocation":"C:\\Users\\alejo\\Desktop\\SportsMatch\\sportsmatch\\client\\assets","httpServerLocation":"/assets/assets","width":352,"height":441,"scales":[1],"files":["C:\\Users\\alejo\\Desktop\\SportsMatch\\sportsmatch\\client\\assets\\hannahredingkqyboqrw5wunsplash-11.png"],"hash":"64954ec97ee5b23a0df87f0932e2bafa","name":"hannahredingkqyboqrw5wunsplash-11","type":"png","fileHashes":["64954ec97ee5b23a0df87f0932e2bafa"]},"dfd169a3d2843dc3aedb26a9ea5bcd9f":{"__packager_asset":true,"fileSystemLocation":"C:\\Users\\alejo\\Desktop\\SportsMatch\\sportsmatch\\client\\assets","httpServerLocation":"/assets/assets","width":352,"height":440,"scales":[1],"files":["C:\\Users\\alejo\\Desktop\\SportsMatch\\sportsmatch\\client\\assets\\hannahredingkqyboqrw5wunsplash-21.png"],"hash":"dfd169a3d2843dc3aedb26a9ea5bcd9f","name":"hannahredingkqyboqrw5wunsplash-21","type":"png","fileHashes":["dfd169a3d2843dc3aedb26a9ea5bcd9f"]},"8c01145a658bb473c6768c2407fba958":{"__packager_asset":true,"fileSystemLocation":"C:\\Users\\alejo\\Desktop\\SportsMatch\\sportsmatch\\client\\assets","httpServerLocation":"/assets/assets","width":721,"height":889,"scales":[1],"files":["C:\\Users\\alejo\\Desktop\\SportsMatch\\sportsmatch\\client\\assets\\nickfithenbuugssofvounsplash-11.png"],"hash":"8c01145a658bb473c6768c2407fba958","name":"nickfithenbuugssofvounsplash-11","type":"png","fileHashes":["8c01145a658bb473c6768c2407fba958"]},"7e860e97989724a217f0f3de96228d3a":{"__packager_asset":true,"fileSystemLocation":"C:\\Users\\alejo\\Desktop\\SportsMatch\\sportsmatch\\client\\assets","httpServerLocation":"/assets/assets","width":456,"height":12,"scales":[1],"files":["C:\\Users\\alejo\\Desktop\\SportsMatch\\sportsmatch\\client\\assets\\line-9.png"],"hash":"7e860e97989724a217f0f3de96228d3a","name":"line-9","type":"png","fileHashes":["7e860e97989724a217f0f3de96228d3a"]},"d07bbedf8492bf77aafd7dc8e2e496d8":{"__packager_asset":true,"fileSystemLocation":"C:\\Users\\alejo\\Desktop\\SportsMatch\\sportsmatch\\client\\assets","httpServerLocation":"/assets/assets","width":105,"height":105,"scales":[1],"files":["C:\\Users\\alejo\\Desktop\\SportsMatch\\sportsmatch\\client\\assets\\mask-group1.png"],"hash":"d07bbedf8492bf77aafd7dc8e2e496d8","name":"mask-group1","type":"png","fileHashes":["d07bbedf8492bf77aafd7dc8e2e496d8"]},"4eb666628cf678a9f7388bef69d4b608":{"__packager_asset":true,"fileSystemLocation":"C:\\Users\\alejo\\Desktop\\SportsMatch\\sportsmatch\\client\\assets","httpServerLocation":"/assets/assets","width":93,"height":91,"scales":[1],"files":["C:\\Users\\alejo\\Desktop\\SportsMatch\\sportsmatch\\client\\assets\\group-535.png"],"hash":"4eb666628cf678a9f7388bef69d4b608","name":"group-535","type":"png","fileHashes":["4eb666628cf678a9f7388bef69d4b608"]},"86deb928fc9efed4b16ada1cf55406a9":{"__packager_asset":true,"fileSystemLocation":"C:\\Users\\alejo\\Desktop\\SportsMatch\\sportsmatch\\client\\assets","httpServerLocation":"/assets/assets","width":1,"height":234,"scales":[1],"files":["C:\\Users\\alejo\\Desktop\\SportsMatch\\sportsmatch\\client\\assets\\line-5.png"],"hash":"86deb928fc9efed4b16ada1cf55406a9","name":"line-5","type":"png","fileHashes":["86deb928fc9efed4b16ada1cf55406a9"]},"60b17d8b64e9b099e8726c4341303500":{"__packager_asset":true,"fileSystemLocation":"C:\\Users\\alejo\\Desktop\\SportsMatch\\sportsmatch\\client\\assets","httpServerLocation":"/assets/assets","width":99,"height":93,"scales":[1],"files":["C:\\Users\\alejo\\Desktop\\SportsMatch\\sportsmatch\\client\\assets\\group-540.png"],"hash":"60b17d8b64e9b099e8726c4341303500","name":"group-540","type":"png","fileHashes":["60b17d8b64e9b099e8726c4341303500"]},"d4c4fe422f1b159eaadf77d4b8fe4451":{"__packager_asset":true,"fileSystemLocation":"C:\\Users\\alejo\\Desktop\\SportsMatch\\sportsmatch\\client\\assets","httpServerLocation":"/assets/assets","width":102,"height":69,"scales":[1],"files":["C:\\Users\\alejo\\Desktop\\SportsMatch\\sportsmatch\\client\\assets\\group-539.png"],"hash":"d4c4fe422f1b159eaadf77d4b8fe4451","name":"group-539","type":"png","fileHashes":["d4c4fe422f1b159eaadf77d4b8fe4451"]},"b08ef048efbf5b3f4a7775106ddb7e8c":{"__packager_asset":true,"fileSystemLocation":"C:\\Users\\alejo\\Desktop\\SportsMatch\\sportsmatch\\client\\assets","httpServerLocation":"/assets/assets","width":105,"height":105,"scales":[1],"files":["C:\\Users\\alejo\\Desktop\\SportsMatch\\sportsmatch\\client\\assets\\group-593.png"],"hash":"b08ef048efbf5b3f4a7775106ddb7e8c","name":"group-593","type":"png","fileHashes":["b08ef048efbf5b3f4a7775106ddb7e8c"]},"18de7cbd2b377c1a3cf44e5fc25adf66":{"__packager_asset":true,"fileSystemLocation":"C:\\Users\\alejo\\Desktop\\SportsMatch\\sportsmatch\\client\\assets","httpServerLocation":"/assets/assets","width":15,"height":15,"scales":[1],"files":["C:\\Users\\alejo\\Desktop\\SportsMatch\\sportsmatch\\client\\assets\\ellipse-83.png"],"hash":"18de7cbd2b377c1a3cf44e5fc25adf66","name":"ellipse-83","type":"png","fileHashes":["18de7cbd2b377c1a3cf44e5fc25adf66"]},"76166e4a92e601ffc5694c343e24efe0":{"__packager_asset":true,"fileSystemLocation":"C:\\Users\\alejo\\Desktop\\SportsMatch\\sportsmatch\\client\\assets","httpServerLocation":"/assets/assets","width":560,"height":132,"scales":[1],"files":["C:\\Users\\alejo\\Desktop\\SportsMatch\\sportsmatch\\client\\assets\\logo.png"],"hash":"76166e4a92e601ffc5694c343e24efe0","name":"logo","type":"png","fileHashes":["76166e4a92e601ffc5694c343e24efe0"]},"eaeb88449c7cbaed66571f483c49c3df":{"__packager_asset":true,"fileSystemLocation":"C:\\Users\\alejo\\Desktop\\SportsMatch\\sportsmatch\\client\\assets","httpServerLocation":"/assets/assets","width":43,"height":42,"scales":[1],"files":["C:\\Users\\alejo\\Desktop\\SportsMatch\\sportsmatch\\client\\assets\\ellipse-81.png"],"hash":"eaeb88449c7cbaed66571f483c49c3df","name":"ellipse-81","type":"png","fileHashes":["eaeb88449c7cbaed66571f483c49c3df"]},"da384141db5a1c8ff3efd64a783ff58c":{"__packager_asset":true,"fileSystemLocation":"C:\\Users\\alejo\\Desktop\\SportsMatch\\sportsmatch\\client\\assets","httpServerLocation":"/assets/assets","width":361,"height":135,"scales":[1],"files":["C:\\Users\\alejo\\Desktop\\SportsMatch\\sportsmatch\\client\\assets\\rectangle-176.png"],"hash":"da384141db5a1c8ff3efd64a783ff58c","name":"rectangle-176","type":"png","fileHashes":["da384141db5a1c8ff3efd64a783ff58c"]},"0cfeec30ec0b1c91de5db40cb6915480":{"__packager_asset":true,"fileSystemLocation":"C:\\Users\\alejo\\Desktop\\SportsMatch\\sportsmatch\\client\\assets","httpServerLocation":"/assets/assets","width":101,"height":78,"scales":[1],"files":["C:\\Users\\alejo\\Desktop\\SportsMatch\\sportsmatch\\client\\assets\\group4.png"],"hash":"0cfeec30ec0b1c91de5db40cb6915480","name":"group4","type":"png","fileHashes":["0cfeec30ec0b1c91de5db40cb6915480"]},"60d35defa6fda57a31286774cc0ecb31":{"__packager_asset":true,"fileSystemLocation":"C:\\Users\\alejo\\Desktop\\SportsMatch\\sportsmatch\\client\\assets","httpServerLocation":"/assets/assets","width":7,"height":131,"scales":[1],"files":["C:\\Users\\alejo\\Desktop\\SportsMatch\\sportsmatch\\client\\assets\\line-21.png"],"hash":"60d35defa6fda57a31286774cc0ecb31","name":"line-21","type":"png","fileHashes":["60d35defa6fda57a31286774cc0ecb31"]},"4d87c3eba8660bdb1bf7ce8bfe4833f6":{"__packager_asset":true,"fileSystemLocation":"C:\\Users\\alejo\\Desktop\\SportsMatch\\sportsmatch\\client\\assets","httpServerLocation":"/assets/assets","width":94,"height":94,"scales":[1],"files":["C:\\Users\\alejo\\Desktop\\SportsMatch\\sportsmatch\\client\\assets\\group-658.png"],"hash":"4d87c3eba8660bdb1bf7ce8bfe4833f6","name":"group-658","type":"png","fileHashes":["4d87c3eba8660bdb1bf7ce8bfe4833f6"]},"b040423ad4b3ff0230b5486734ebb02c":{"__packager_asset":true,"fileSystemLocation":"C:\\Users\\alejo\\Desktop\\SportsMatch\\sportsmatch\\client\\assets","httpServerLocation":"/assets/assets","width":43,"height":45,"scales":[1],"files":["C:\\Users\\alejo\\Desktop\\SportsMatch\\sportsmatch\\client\\assets\\group-428.png"],"hash":"b040423ad4b3ff0230b5486734ebb02c","name":"group-428","type":"png","fileHashes":["b040423ad4b3ff0230b5486734ebb02c"]},"be5b58b0ffb5463352deeb5f9a7e97cb":{"__packager_asset":true,"fileSystemLocation":"C:\\Users\\alejo\\Desktop\\SportsMatch\\sportsmatch\\client\\assets","httpServerLocation":"/assets/assets","width":68,"height":51,"scales":[1],"files":["C:\\Users\\alejo\\Desktop\\SportsMatch\\sportsmatch\\client\\assets\\group5.png"],"hash":"be5b58b0ffb5463352deeb5f9a7e97cb","name":"group5","type":"png","fileHashes":["be5b58b0ffb5463352deeb5f9a7e97cb"]},"98cf9325ca7cebfe4b7b1911812c3d6e":{"__packager_asset":true,"fileSystemLocation":"C:\\Users\\alejo\\Desktop\\SportsMatch\\sportsmatch\\client\\assets","httpServerLocation":"/assets/assets","width":34,"height":27,"scales":[1],"files":["C:\\Users\\alejo\\Desktop\\SportsMatch\\sportsmatch\\client\\assets\\vector-16.png"],"hash":"98cf9325ca7cebfe4b7b1911812c3d6e","name":"vector-16","type":"png","fileHashes":["98cf9325ca7cebfe4b7b1911812c3d6e"]},"7f3a86497350415a9aa7277a24ffadcf":{"__packager_asset":true,"fileSystemLocation":"C:\\Users\\alejo\\Desktop\\SportsMatch\\sportsmatch\\client\\assets","httpServerLocation":"/assets/assets","width":42,"height":53,"scales":[1],"files":["C:\\Users\\alejo\\Desktop\\SportsMatch\\sportsmatch\\client\\assets\\pictograma.png"],"hash":"7f3a86497350415a9aa7277a24ffadcf","name":"pictograma","type":"png","fileHashes":["7f3a86497350415a9aa7277a24ffadcf"]},"5ba024ea1c4c3e66963e92b109150ad8":{"__packager_asset":true,"fileSystemLocation":"C:\\Users\\alejo\\Desktop\\SportsMatch\\sportsmatch\\client\\assets","httpServerLocation":"/assets/assets","width":49,"height":49,"scales":[1],"files":["C:\\Users\\alejo\\Desktop\\SportsMatch\\sportsmatch\\client\\assets\\group6.png"],"hash":"5ba024ea1c4c3e66963e92b109150ad8","name":"group6","type":"png","fileHashes":["5ba024ea1c4c3e66963e92b109150ad8"]},"cd544750b2aa4c9fd3a143ec9df134e5":{"__packager_asset":true,"fileSystemLocation":"C:\\Users\\alejo\\Desktop\\SportsMatch\\sportsmatch\\client\\assets","httpServerLocation":"/assets/assets","width":5,"height":13,"scales":[1],"files":["C:\\Users\\alejo\\Desktop\\SportsMatch\\sportsmatch\\client\\assets\\cap.png"],"hash":"cd544750b2aa4c9fd3a143ec9df134e5","name":"cap","type":"png","fileHashes":["cd544750b2aa4c9fd3a143ec9df134e5"]},"8b6ef1c327a0583c698e329a35100805":{"__packager_asset":true,"fileSystemLocation":"C:\\Users\\alejo\\Desktop\\SportsMatch\\sportsmatch\\client\\assets","httpServerLocation":"/assets/assets","width":48,"height":34,"scales":[1],"files":["C:\\Users\\alejo\\Desktop\\SportsMatch\\sportsmatch\\client\\assets\\wifi2.png"],"hash":"8b6ef1c327a0583c698e329a35100805","name":"wifi2","type":"png","fileHashes":["8b6ef1c327a0583c698e329a35100805"]},"9cded6a2068ba9b6932ebbf740c02adf":{"__packager_asset":true,"fileSystemLocation":"C:\\Users\\alejo\\Desktop\\SportsMatch\\sportsmatch\\client\\assets","httpServerLocation":"/assets/assets","width":53,"height":33,"scales":[1],"files":["C:\\Users\\alejo\\Desktop\\SportsMatch\\sportsmatch\\client\\assets\\cellular-connection.png"],"hash":"9cded6a2068ba9b6932ebbf740c02adf","name":"cellular-connection","type":"png","fileHashes":["9cded6a2068ba9b6932ebbf740c02adf"]},"47f75e07e2106f162805dce5df32c2ee":{"__packager_asset":true,"fileSystemLocation":"C:\\Users\\alejo\\Desktop\\SportsMatch\\sportsmatch\\client\\assets","httpServerLocation":"/assets/assets","width":27,"height":46,"scales":[1],"files":["C:\\Users\\alejo\\Desktop\\SportsMatch\\sportsmatch\\client\\assets\\coolicon3.png"],"hash":"47f75e07e2106f162805dce5df32c2ee","name":"coolicon3","type":"png","fileHashes":["47f75e07e2106f162805dce5df32c2ee"]},"03f2ecfca6b2338758e88b65ea43e230":{"__packager_asset":true,"fileSystemLocation":"C:\\Users\\alejo\\Desktop\\SportsMatch\\sportsmatch\\client\\assets","httpServerLocation":"/assets/assets","width":1080,"height":1200,"scales":[1],"files":["C:\\Users\\alejo\\Desktop\\SportsMatch\\sportsmatch\\client\\assets\\group-4891.png"],"hash":"03f2ecfca6b2338758e88b65ea43e230","name":"group-4891","type":"png","fileHashes":["03f2ecfca6b2338758e88b65ea43e230"]},"c78b892b8c7e9af232aec516f03f4627":{"__packager_asset":true,"fileSystemLocation":"C:\\Users\\alejo\\Desktop\\SportsMatch\\sportsmatch\\client\\assets","httpServerLocation":"/assets/assets","width":564,"height":10,"scales":[1],"files":["C:\\Users\\alejo\\Desktop\\SportsMatch\\sportsmatch\\client\\assets\\line-6.png"],"hash":"c78b892b8c7e9af232aec516f03f4627","name":"line-6","type":"png","fileHashes":["c78b892b8c7e9af232aec516f03f4627"]},"d7e561e42bece27b60d5fa8b5fba7e53":{"__packager_asset":true,"fileSystemLocation":"C:\\Users\\alejo\\Desktop\\SportsMatch\\sportsmatch\\client\\assets","httpServerLocation":"/assets/assets","width":1080,"height":990,"scales":[1],"files":["C:\\Users\\alejo\\Desktop\\SportsMatch\\sportsmatch\\client\\assets\\group-4892.png"],"hash":"d7e561e42bece27b60d5fa8b5fba7e53","name":"group-4892","type":"png","fileHashes":["d7e561e42bece27b60d5fa8b5fba7e53"]},"6706b81476b5c507cb78e81962e68fed":{"__packager_asset":true,"fileSystemLocation":"C:\\Users\\alejo\\Desktop\\SportsMatch\\sportsmatch\\client\\assets","httpServerLocation":"/assets/assets","width":366,"height":54,"scales":[1],"files":["C:\\Users\\alejo\\Desktop\\SportsMatch\\sportsmatch\\client\\assets\\group-691.png"],"hash":"6706b81476b5c507cb78e81962e68fed","name":"group-691","type":"png","fileHashes":["6706b81476b5c507cb78e81962e68fed"]},"5a7f656e8da3db7998a73468480727c7":{"__packager_asset":true,"fileSystemLocation":"C:\\Users\\alejo\\Desktop\\SportsMatch\\sportsmatch\\client\\assets","httpServerLocation":"/assets/assets","width":366,"height":54,"scales":[1],"files":["C:\\Users\\alejo\\Desktop\\SportsMatch\\sportsmatch\\client\\assets\\group-692.png"],"hash":"5a7f656e8da3db7998a73468480727c7","name":"group-692","type":"png","fileHashes":["5a7f656e8da3db7998a73468480727c7"]},"25053cf428363f5bbf19841bd138ef11":{"__packager_asset":true,"fileSystemLocation":"C:\\Users\\alejo\\Desktop\\SportsMatch\\sportsmatch\\client\\assets","httpServerLocation":"/assets/assets","width":48,"height":34,"scales":[1],"files":["C:\\Users\\alejo\\Desktop\\SportsMatch\\sportsmatch\\client\\assets\\wifi1.png"],"hash":"25053cf428363f5bbf19841bd138ef11","name":"wifi1","type":"png","fileHashes":["25053cf428363f5bbf19841bd138ef11"]},"2bfd388c1ef9b42b11fda93f8f26135f":{"__packager_asset":true,"fileSystemLocation":"C:\\Users\\alejo\\Desktop\\SportsMatch\\sportsmatch\\client\\assets","httpServerLocation":"/assets/assets","width":53,"height":33,"scales":[1],"files":["C:\\Users\\alejo\\Desktop\\SportsMatch\\sportsmatch\\client\\assets\\cellular-connection2.png"],"hash":"2bfd388c1ef9b42b11fda93f8f26135f","name":"cellular-connection2","type":"png","fileHashes":["2bfd388c1ef9b42b11fda93f8f26135f"]},"4bd344ee41d8fb601739d96067c6ca63":{"__packager_asset":true,"fileSystemLocation":"C:\\Users\\alejo\\Desktop\\SportsMatch\\sportsmatch\\client\\assets","httpServerLocation":"/assets/assets","width":67,"height":50,"scales":[1],"files":["C:\\Users\\alejo\\Desktop\\SportsMatch\\sportsmatch\\client\\assets\\pictograma-filtros.png"],"hash":"4bd344ee41d8fb601739d96067c6ca63","name":"pictograma-filtros","type":"png","fileHashes":["4bd344ee41d8fb601739d96067c6ca63"]},"82d5bf80d4902bdc4813e3a873592c2f":{"__packager_asset":true,"fileSystemLocation":"C:\\Users\\alejo\\Desktop\\SportsMatch\\sportsmatch\\client\\assets","httpServerLocation":"/assets/assets","width":105,"height":105,"scales":[1],"files":["C:\\Users\\alejo\\Desktop\\SportsMatch\\sportsmatch\\client\\assets\\mask-group7.png"],"hash":"82d5bf80d4902bdc4813e3a873592c2f","name":"mask-group7","type":"png","fileHashes":["82d5bf80d4902bdc4813e3a873592c2f"]},"c14c5dcf1982f4a1da559bef36a893a7":{"__packager_asset":true,"fileSystemLocation":"C:\\Users\\alejo\\Desktop\\SportsMatch\\sportsmatch\\client\\assets","httpServerLocation":"/assets/assets","width":99,"height":93,"scales":[1],"files":["C:\\Users\\alejo\\Desktop\\SportsMatch\\sportsmatch\\client\\assets\\group-5401.png"],"hash":"c14c5dcf1982f4a1da559bef36a893a7","name":"group-5401","type":"png","fileHashes":["c14c5dcf1982f4a1da559bef36a893a7"]},"28332f706cd4d42bdbc5677d1836585d":{"__packager_asset":true,"fileSystemLocation":"C:\\Users\\alejo\\Desktop\\SportsMatch\\sportsmatch\\client\\assets","httpServerLocation":"/assets/assets","width":102,"height":69,"scales":[1],"files":["C:\\Users\\alejo\\Desktop\\SportsMatch\\sportsmatch\\client\\assets\\group-5391.png"],"hash":"28332f706cd4d42bdbc5677d1836585d","name":"group-5391","type":"png","fileHashes":["28332f706cd4d42bdbc5677d1836585d"]},"3a2ba31570920eeb9b1d217cabe58315":{"__packager_asset":true,"fileSystemLocation":"C:\\Users\\alejo\\Desktop\\SportsMatch\\sportsmatch\\client\\node_modules\\@expo\\vector-icons\\build\\vendor\\react-native-vector-icons\\Fonts","httpServerLocation":"/assets/node_modules/@expo/vector-icons/build/vendor/react-native-vector-icons/Fonts","scales":[1],"files":["C:\\Users\\alejo\\Desktop\\SportsMatch\\sportsmatch\\client\\node_modules\\@expo\\vector-icons\\build\\vendor\\react-native-vector-icons\\Fonts\\AntDesign.ttf"],"hash":"3a2ba31570920eeb9b1d217cabe58315","name":"AntDesign","type":"ttf","fileHashes":["3a2ba31570920eeb9b1d217cabe58315"]},"31b5ffea3daddc69dd01a1f3d6cf63c5":{"__packager_asset":true,"fileSystemLocation":"C:\\Users\\alejo\\Desktop\\SportsMatch\\sportsmatch\\client\\node_modules\\@expo\\vector-icons\\build\\vendor\\react-native-vector-icons\\Fonts","httpServerLocation":"/assets/node_modules/@expo/vector-icons/build/vendor/react-native-vector-icons/Fonts","scales":[1],"files":["C:\\Users\\alejo\\Desktop\\SportsMatch\\sportsmatch\\client\\node_modules\\@expo\\vector-icons\\build\\vendor\\react-native-vector-icons\\Fonts\\Entypo.ttf"],"hash":"31b5ffea3daddc69dd01a1f3d6cf63c5","name":"Entypo","type":"ttf","fileHashes":["31b5ffea3daddc69dd01a1f3d6cf63c5"]},"140c53a7643ea949007aa9a282153849":{"__packager_asset":true,"fileSystemLocation":"C:\\Users\\alejo\\Desktop\\SportsMatch\\sportsmatch\\client\\node_modules\\@expo\\vector-icons\\build\\vendor\\react-native-vector-icons\\Fonts","httpServerLocation":"/assets/node_modules/@expo/vector-icons/build/vendor/react-native-vector-icons/Fonts","scales":[1],"files":["C:\\Users\\alejo\\Desktop\\SportsMatch\\sportsmatch\\client\\node_modules\\@expo\\vector-icons\\build\\vendor\\react-native-vector-icons\\Fonts\\EvilIcons.ttf"],"hash":"140c53a7643ea949007aa9a282153849","name":"EvilIcons","type":"ttf","fileHashes":["140c53a7643ea949007aa9a282153849"]},"a76d309774d33d9856f650bed4292a23":{"__packager_asset":true,"fileSystemLocation":"C:\\Users\\alejo\\Desktop\\SportsMatch\\sportsmatch\\client\\node_modules\\@expo\\vector-icons\\build\\vendor\\react-native-vector-icons\\Fonts","httpServerLocation":"/assets/node_modules/@expo/vector-icons/build/vendor/react-native-vector-icons/Fonts","scales":[1],"files":["C:\\Users\\alejo\\Desktop\\SportsMatch\\sportsmatch\\client\\node_modules\\@expo\\vector-icons\\build\\vendor\\react-native-vector-icons\\Fonts\\Feather.ttf"],"hash":"a76d309774d33d9856f650bed4292a23","name":"Feather","type":"ttf","fileHashes":["a76d309774d33d9856f650bed4292a23"]},"b49ae8ab2dbccb02c4d11caaacf09eab":{"__packager_asset":true,"fileSystemLocation":"C:\\Users\\alejo\\Desktop\\SportsMatch\\sportsmatch\\client\\node_modules\\@expo\\vector-icons\\build\\vendor\\react-native-vector-icons\\Fonts","httpServerLocation":"/assets/node_modules/@expo/vector-icons/build/vendor/react-native-vector-icons/Fonts","scales":[1],"files":["C:\\Users\\alejo\\Desktop\\SportsMatch\\sportsmatch\\client\\node_modules\\@expo\\vector-icons\\build\\vendor\\react-native-vector-icons\\Fonts\\Fontisto.ttf"],"hash":"b49ae8ab2dbccb02c4d11caaacf09eab","name":"Fontisto","type":"ttf","fileHashes":["b49ae8ab2dbccb02c4d11caaacf09eab"]},"b06871f281fee6b241d60582ae9369b9":{"__packager_asset":true,"fileSystemLocation":"C:\\Users\\alejo\\Desktop\\SportsMatch\\sportsmatch\\client\\node_modules\\@expo\\vector-icons\\build\\vendor\\react-native-vector-icons\\Fonts","httpServerLocation":"/assets/node_modules/@expo/vector-icons/build/vendor/react-native-vector-icons/Fonts","scales":[1],"files":["C:\\Users\\alejo\\Desktop\\SportsMatch\\sportsmatch\\client\\node_modules\\@expo\\vector-icons\\build\\vendor\\react-native-vector-icons\\Fonts\\FontAwesome.ttf"],"hash":"b06871f281fee6b241d60582ae9369b9","name":"FontAwesome","type":"ttf","fileHashes":["b06871f281fee6b241d60582ae9369b9"]},"1f77739ca9ff2188b539c36f30ffa2be":{"__packager_asset":true,"fileSystemLocation":"C:\\Users\\alejo\\Desktop\\SportsMatch\\sportsmatch\\client\\node_modules\\@expo\\vector-icons\\build\\vendor\\react-native-vector-icons\\Fonts","httpServerLocation":"/assets/node_modules/@expo/vector-icons/build/vendor/react-native-vector-icons/Fonts","scales":[1],"files":["C:\\Users\\alejo\\Desktop\\SportsMatch\\sportsmatch\\client\\node_modules\\@expo\\vector-icons\\build\\vendor\\react-native-vector-icons\\Fonts\\FontAwesome5_Regular.ttf"],"hash":"1f77739ca9ff2188b539c36f30ffa2be","name":"FontAwesome5_Regular","type":"ttf","fileHashes":["1f77739ca9ff2188b539c36f30ffa2be"]},"605ed7926cf39a2ad5ec2d1f9d391d3d":{"__packager_asset":true,"fileSystemLocation":"C:\\Users\\alejo\\Desktop\\SportsMatch\\sportsmatch\\client\\node_modules\\@expo\\vector-icons\\build\\vendor\\react-native-vector-icons\\Fonts","httpServerLocation":"/assets/node_modules/@expo/vector-icons/build/vendor/react-native-vector-icons/Fonts","scales":[1],"files":["C:\\Users\\alejo\\Desktop\\SportsMatch\\sportsmatch\\client\\node_modules\\@expo\\vector-icons\\build\\vendor\\react-native-vector-icons\\Fonts\\FontAwesome5_Solid.ttf"],"hash":"605ed7926cf39a2ad5ec2d1f9d391d3d","name":"FontAwesome5_Solid","type":"ttf","fileHashes":["605ed7926cf39a2ad5ec2d1f9d391d3d"]},"3b89dd103490708d19a95adcae52210e":{"__packager_asset":true,"fileSystemLocation":"C:\\Users\\alejo\\Desktop\\SportsMatch\\sportsmatch\\client\\node_modules\\@expo\\vector-icons\\build\\vendor\\react-native-vector-icons\\Fonts","httpServerLocation":"/assets/node_modules/@expo/vector-icons/build/vendor/react-native-vector-icons/Fonts","scales":[1],"files":["C:\\Users\\alejo\\Desktop\\SportsMatch\\sportsmatch\\client\\node_modules\\@expo\\vector-icons\\build\\vendor\\react-native-vector-icons\\Fonts\\FontAwesome5_Brands.ttf"],"hash":"3b89dd103490708d19a95adcae52210e","name":"FontAwesome5_Brands","type":"ttf","fileHashes":["3b89dd103490708d19a95adcae52210e"]},"675809e48e35c47d51c7d6fcc687ee28":{"__packager_asset":true,"fileSystemLocation":"C:\\Users\\alejo\\Desktop\\SportsMatch\\sportsmatch\\client\\node_modules\\@expo\\vector-icons\\build\\vendor\\react-native-vector-icons\\Fonts","httpServerLocation":"/assets/node_modules/@expo/vector-icons/build/vendor/react-native-vector-icons/Fonts","scales":[1],"files":["C:\\Users\\alejo\\Desktop\\SportsMatch\\sportsmatch\\client\\node_modules\\@expo\\vector-icons\\build\\vendor\\react-native-vector-icons\\Fonts\\FontAwesome6_Regular.ttf"],"hash":"675809e48e35c47d51c7d6fcc687ee28","name":"FontAwesome6_Regular","type":"ttf","fileHashes":["675809e48e35c47d51c7d6fcc687ee28"]},"0248ab19e74fc3731de14d647db4687a":{"__packager_asset":true,"fileSystemLocation":"C:\\Users\\alejo\\Desktop\\SportsMatch\\sportsmatch\\client\\node_modules\\@expo\\vector-icons\\build\\vendor\\react-native-vector-icons\\Fonts","httpServerLocation":"/assets/node_modules/@expo/vector-icons/build/vendor/react-native-vector-icons/Fonts","scales":[1],"files":["C:\\Users\\alejo\\Desktop\\SportsMatch\\sportsmatch\\client\\node_modules\\@expo\\vector-icons\\build\\vendor\\react-native-vector-icons\\Fonts\\FontAwesome6_Solid.ttf"],"hash":"0248ab19e74fc3731de14d647db4687a","name":"FontAwesome6_Solid","type":"ttf","fileHashes":["0248ab19e74fc3731de14d647db4687a"]},"bb8cd014d7a55672934233c354e1c4a3":{"__packager_asset":true,"fileSystemLocation":"C:\\Users\\alejo\\Desktop\\SportsMatch\\sportsmatch\\client\\node_modules\\@expo\\vector-icons\\build\\vendor\\react-native-vector-icons\\Fonts","httpServerLocation":"/assets/node_modules/@expo/vector-icons/build/vendor/react-native-vector-icons/Fonts","scales":[1],"files":["C:\\Users\\alejo\\Desktop\\SportsMatch\\sportsmatch\\client\\node_modules\\@expo\\vector-icons\\build\\vendor\\react-native-vector-icons\\Fonts\\FontAwesome6_Brands.ttf"],"hash":"bb8cd014d7a55672934233c354e1c4a3","name":"FontAwesome6_Brands","type":"ttf","fileHashes":["bb8cd014d7a55672934233c354e1c4a3"]},"e20945d7c929279ef7a6f1db184a4470":{"__packager_asset":true,"fileSystemLocation":"C:\\Users\\alejo\\Desktop\\SportsMatch\\sportsmatch\\client\\node_modules\\@expo\\vector-icons\\build\\vendor\\react-native-vector-icons\\Fonts","httpServerLocation":"/assets/node_modules/@expo/vector-icons/build/vendor/react-native-vector-icons/Fonts","scales":[1],"files":["C:\\Users\\alejo\\Desktop\\SportsMatch\\sportsmatch\\client\\node_modules\\@expo\\vector-icons\\build\\vendor\\react-native-vector-icons\\Fonts\\Foundation.ttf"],"hash":"e20945d7c929279ef7a6f1db184a4470","name":"Foundation","type":"ttf","fileHashes":["e20945d7c929279ef7a6f1db184a4470"]},"6148e7019854f3bde85b633cb88f3c25":{"__packager_asset":true,"fileSystemLocation":"C:\\Users\\alejo\\Desktop\\SportsMatch\\sportsmatch\\client\\node_modules\\@expo\\vector-icons\\build\\vendor\\react-native-vector-icons\\Fonts","httpServerLocation":"/assets/node_modules/@expo/vector-icons/build/vendor/react-native-vector-icons/Fonts","scales":[1],"files":["C:\\Users\\alejo\\Desktop\\SportsMatch\\sportsmatch\\client\\node_modules\\@expo\\vector-icons\\build\\vendor\\react-native-vector-icons\\Fonts\\Ionicons.ttf"],"hash":"6148e7019854f3bde85b633cb88f3c25","name":"Ionicons","type":"ttf","fileHashes":["6148e7019854f3bde85b633cb88f3c25"]},"b62641afc9ab487008e996a5c5865e56":{"__packager_asset":true,"fileSystemLocation":"C:\\Users\\alejo\\Desktop\\SportsMatch\\sportsmatch\\client\\node_modules\\@expo\\vector-icons\\build\\vendor\\react-native-vector-icons\\Fonts","httpServerLocation":"/assets/node_modules/@expo/vector-icons/build/vendor/react-native-vector-icons/Fonts","scales":[1],"files":["C:\\Users\\alejo\\Desktop\\SportsMatch\\sportsmatch\\client\\node_modules\\@expo\\vector-icons\\build\\vendor\\react-native-vector-icons\\Fonts\\MaterialCommunityIcons.ttf"],"hash":"b62641afc9ab487008e996a5c5865e56","name":"MaterialCommunityIcons","type":"ttf","fileHashes":["b62641afc9ab487008e996a5c5865e56"]},"4e85bc9ebe07e0340c9c4fc2f6c38908":{"__packager_asset":true,"fileSystemLocation":"C:\\Users\\alejo\\Desktop\\SportsMatch\\sportsmatch\\client\\node_modules\\@expo\\vector-icons\\build\\vendor\\react-native-vector-icons\\Fonts","httpServerLocation":"/assets/node_modules/@expo/vector-icons/build/vendor/react-native-vector-icons/Fonts","scales":[1],"files":["C:\\Users\\alejo\\Desktop\\SportsMatch\\sportsmatch\\client\\node_modules\\@expo\\vector-icons\\build\\vendor\\react-native-vector-icons\\Fonts\\MaterialIcons.ttf"],"hash":"4e85bc9ebe07e0340c9c4fc2f6c38908","name":"MaterialIcons","type":"ttf","fileHashes":["4e85bc9ebe07e0340c9c4fc2f6c38908"]},"f7c53c47a66934504fcbc7cc164895a7":{"__packager_asset":true,"fileSystemLocation":"C:\\Users\\alejo\\Desktop\\SportsMatch\\sportsmatch\\client\\node_modules\\@expo\\vector-icons\\build\\vendor\\react-native-vector-icons\\Fonts","httpServerLocation":"/assets/node_modules/@expo/vector-icons/build/vendor/react-native-vector-icons/Fonts","scales":[1],"files":["C:\\Users\\alejo\\Desktop\\SportsMatch\\sportsmatch\\client\\node_modules\\@expo\\vector-icons\\build\\vendor\\react-native-vector-icons\\Fonts\\Octicons.ttf"],"hash":"f7c53c47a66934504fcbc7cc164895a7","name":"Octicons","type":"ttf","fileHashes":["f7c53c47a66934504fcbc7cc164895a7"]},"d2285965fe34b05465047401b8595dd0":{"__packager_asset":true,"fileSystemLocation":"C:\\Users\\alejo\\Desktop\\SportsMatch\\sportsmatch\\client\\node_modules\\@expo\\vector-icons\\build\\vendor\\react-native-vector-icons\\Fonts","httpServerLocation":"/assets/node_modules/@expo/vector-icons/build/vendor/react-native-vector-icons/Fonts","scales":[1],"files":["C:\\Users\\alejo\\Desktop\\SportsMatch\\sportsmatch\\client\\node_modules\\@expo\\vector-icons\\build\\vendor\\react-native-vector-icons\\Fonts\\SimpleLineIcons.ttf"],"hash":"d2285965fe34b05465047401b8595dd0","name":"SimpleLineIcons","type":"ttf","fileHashes":["d2285965fe34b05465047401b8595dd0"]},"1681f34aaca71b8dfb70756bca331eb2":{"__packager_asset":true,"fileSystemLocation":"C:\\Users\\alejo\\Desktop\\SportsMatch\\sportsmatch\\client\\node_modules\\@expo\\vector-icons\\build\\vendor\\react-native-vector-icons\\Fonts","httpServerLocation":"/assets/node_modules/@expo/vector-icons/build/vendor/react-native-vector-icons/Fonts","scales":[1],"files":["C:\\Users\\alejo\\Desktop\\SportsMatch\\sportsmatch\\client\\node_modules\\@expo\\vector-icons\\build\\vendor\\react-native-vector-icons\\Fonts\\Zocial.ttf"],"hash":"1681f34aaca71b8dfb70756bca331eb2","name":"Zocial","type":"ttf","fileHashes":["1681f34aaca71b8dfb70756bca331eb2"]},"5699a958cd4c7aef8139b30b16b89364":{"__packager_asset":true,"fileSystemLocation":"C:\\Users\\alejo\\Desktop\\SportsMatch\\sportsmatch\\client\\assets","httpServerLocation":"/assets/assets","width":1077,"height":1500,"scales":[1],"files":["C:\\Users\\alejo\\Desktop\\SportsMatch\\sportsmatch\\client\\assets\\fondo-color.png"],"hash":"5699a958cd4c7aef8139b30b16b89364","name":"fondo-color","type":"png","fileHashes":["5699a958cd4c7aef8139b30b16b89364"]},"8d70477b01071ca26bbbd9c6f64a6c41":{"__packager_asset":true,"fileSystemLocation":"C:\\Users\\alejo\\Desktop\\SportsMatch\\sportsmatch\\client\\assets","httpServerLocation":"/assets/assets","width":27,"height":45,"scales":[1],"files":["C:\\Users\\alejo\\Desktop\\SportsMatch\\sportsmatch\\client\\assets\\coolicon4.png"],"hash":"8d70477b01071ca26bbbd9c6f64a6c41","name":"coolicon4","type":"png","fileHashes":["8d70477b01071ca26bbbd9c6f64a6c41"]},"9593c2a26aacfd0417d9ea2e7a5abbe9":{"__packager_asset":true,"fileSystemLocation":"C:\\Users\\alejo\\Desktop\\SportsMatch\\sportsmatch\\client\\assets","httpServerLocation":"/assets/assets","width":1077,"height":1500,"scales":[1],"files":["C:\\Users\\alejo\\Desktop\\SportsMatch\\sportsmatch\\client\\assets\\rectangle-172.png"],"hash":"9593c2a26aacfd0417d9ea2e7a5abbe9","name":"rectangle-172","type":"png","fileHashes":["9593c2a26aacfd0417d9ea2e7a5abbe9"]},"628d9859a5629a8bceac07e7db51d93b":{"__packager_asset":true,"fileSystemLocation":"C:\\Users\\alejo\\Desktop\\SportsMatch\\sportsmatch\\client\\assets","httpServerLocation":"/assets/assets","width":1077,"height":729,"scales":[1],"files":["C:\\Users\\alejo\\Desktop\\SportsMatch\\sportsmatch\\client\\assets\\group-4141.png"],"hash":"628d9859a5629a8bceac07e7db51d93b","name":"group-4141","type":"png","fileHashes":["628d9859a5629a8bceac07e7db51d93b"]},"7c1045a1fd3918f562ff7bf0815457ec":{"__packager_asset":true,"fileSystemLocation":"C:\\Users\\alejo\\Desktop\\SportsMatch\\sportsmatch\\client\\assets","httpServerLocation":"/assets/assets","width":1077,"height":1500,"scales":[1],"files":["C:\\Users\\alejo\\Desktop\\SportsMatch\\sportsmatch\\client\\assets\\mask-group16.png"],"hash":"7c1045a1fd3918f562ff7bf0815457ec","name":"mask-group16","type":"png","fileHashes":["7c1045a1fd3918f562ff7bf0815457ec"]},"b983191dd0bd8434bb9cc0cdd371c5b2":{"__packager_asset":true,"fileSystemLocation":"C:\\Users\\alejo\\Desktop\\SportsMatch\\sportsmatch\\client\\assets","httpServerLocation":"/assets/assets","width":135,"height":135,"scales":[1],"files":["C:\\Users\\alejo\\Desktop\\SportsMatch\\sportsmatch\\client\\assets\\ellipse-762.png"],"hash":"b983191dd0bd8434bb9cc0cdd371c5b2","name":"ellipse-762","type":"png","fileHashes":["b983191dd0bd8434bb9cc0cdd371c5b2"]},"c13cbb3583e9d03fface5b097185997f":{"__packager_asset":true,"fileSystemLocation":"C:\\Users\\alejo\\Desktop\\SportsMatch\\sportsmatch\\client\\assets","httpServerLocation":"/assets/assets","width":105,"height":99,"scales":[1],"files":["C:\\Users\\alejo\\Desktop\\SportsMatch\\sportsmatch\\client\\assets\\logo-uem21removebgpreview-13.png"],"hash":"c13cbb3583e9d03fface5b097185997f","name":"logo-uem21removebgpreview-13","type":"png","fileHashes":["c13cbb3583e9d03fface5b097185997f"]},"34e3fb4ee13c5ee1d0ce511cbb8d5cb8":{"__packager_asset":true,"fileSystemLocation":"C:\\Users\\alejo\\Desktop\\SportsMatch\\sportsmatch\\client\\assets","httpServerLocation":"/assets/assets","width":1074,"height":255,"scales":[1],"files":["C:\\Users\\alejo\\Desktop\\SportsMatch\\sportsmatch\\client\\assets\\fondo-pastilla.png"],"hash":"34e3fb4ee13c5ee1d0ce511cbb8d5cb8","name":"fondo-pastilla","type":"png","fileHashes":["34e3fb4ee13c5ee1d0ce511cbb8d5cb8"]},"c536fbfd41a7f49ef04eb72b3eac24d3":{"__packager_asset":true,"fileSystemLocation":"C:\\Users\\alejo\\Desktop\\SportsMatch\\sportsmatch\\client\\assets","httpServerLocation":"/assets/assets","width":531,"height":15,"scales":[1],"files":["C:\\Users\\alejo\\Desktop\\SportsMatch\\sportsmatch\\client\\assets\\alertas-notificaciones.png"],"hash":"c536fbfd41a7f49ef04eb72b3eac24d3","name":"alertas-notificaciones","type":"png","fileHashes":["c536fbfd41a7f49ef04eb72b3eac24d3"]},"39b456ee3c46f54c0ff7a28037ae00a5":{"__packager_asset":true,"fileSystemLocation":"C:\\Users\\alejo\\Desktop\\SportsMatch\\sportsmatch\\client\\assets","httpServerLocation":"/assets/assets","width":48,"height":34,"scales":[1],"files":["C:\\Users\\alejo\\Desktop\\SportsMatch\\sportsmatch\\client\\assets\\wifi.png"],"hash":"39b456ee3c46f54c0ff7a28037ae00a5","name":"wifi","type":"png","fileHashes":["39b456ee3c46f54c0ff7a28037ae00a5"]},"9e509c2ba6da1883084ba523e15e6f60":{"__packager_asset":true,"fileSystemLocation":"C:\\Users\\alejo\\Desktop\\SportsMatch\\sportsmatch\\client\\assets","httpServerLocation":"/assets/assets","width":53,"height":33,"scales":[1],"files":["C:\\Users\\alejo\\Desktop\\SportsMatch\\sportsmatch\\client\\assets\\cellular-connection4.png"],"hash":"9e509c2ba6da1883084ba523e15e6f60","name":"cellular-connection4","type":"png","fileHashes":["9e509c2ba6da1883084ba523e15e6f60"]},"395bb5251072ec66ef8e8e7b047e8e57":{"__packager_asset":true,"fileSystemLocation":"C:\\Users\\alejo\\Desktop\\SportsMatch\\sportsmatch\\client\\assets","httpServerLocation":"/assets/assets","width":99,"height":93,"scales":[1],"files":["C:\\Users\\alejo\\Desktop\\SportsMatch\\sportsmatch\\client\\assets\\group-5402.png"],"hash":"395bb5251072ec66ef8e8e7b047e8e57","name":"group-5402","type":"png","fileHashes":["395bb5251072ec66ef8e8e7b047e8e57"]},"6c366bc306c5c43cbd37299cda71bea0":{"__packager_asset":true,"fileSystemLocation":"C:\\Users\\alejo\\Desktop\\SportsMatch\\sportsmatch\\client\\assets","httpServerLocation":"/assets/assets","width":102,"height":69,"scales":[1],"files":["C:\\Users\\alejo\\Desktop\\SportsMatch\\sportsmatch\\client\\assets\\group-5393.png"],"hash":"6c366bc306c5c43cbd37299cda71bea0","name":"group-5393","type":"png","fileHashes":["6c366bc306c5c43cbd37299cda71bea0"]},"41990e8800347e983c12cc11b27a057f":{"__packager_asset":true,"fileSystemLocation":"C:\\Users\\alejo\\Desktop\\SportsMatch\\sportsmatch\\client\\assets","httpServerLocation":"/assets/assets","width":4,"height":233,"scales":[1],"files":["C:\\Users\\alejo\\Desktop\\SportsMatch\\sportsmatch\\client\\assets\\line-51.png"],"hash":"41990e8800347e983c12cc11b27a057f","name":"line-51","type":"png","fileHashes":["41990e8800347e983c12cc11b27a057f"]},"b3e0cd95b258dae792042465b1d041b0":{"__packager_asset":true,"fileSystemLocation":"C:\\Users\\alejo\\Desktop\\SportsMatch\\sportsmatch\\client\\assets","httpServerLocation":"/assets/assets","width":3,"height":233,"scales":[1],"files":["C:\\Users\\alejo\\Desktop\\SportsMatch\\sportsmatch\\client\\assets\\line-7.png"],"hash":"b3e0cd95b258dae792042465b1d041b0","name":"line-7","type":"png","fileHashes":["b3e0cd95b258dae792042465b1d041b0"]},"dc7344276140628fb1cc94d15e69f2ee":{"__packager_asset":true,"fileSystemLocation":"C:\\Users\\alejo\\Desktop\\SportsMatch\\sportsmatch\\client\\assets","httpServerLocation":"/assets/assets","width":231,"height":9,"scales":[1],"files":["C:\\Users\\alejo\\Desktop\\SportsMatch\\sportsmatch\\client\\assets\\line-61.png"],"hash":"dc7344276140628fb1cc94d15e69f2ee","name":"line-61","type":"png","fileHashes":["dc7344276140628fb1cc94d15e69f2ee"]},"69ecc6e9be57a6822ffb7a70ff5aa108":{"__packager_asset":true,"fileSystemLocation":"C:\\Users\\alejo\\Desktop\\SportsMatch\\sportsmatch\\client\\assets","httpServerLocation":"/assets/assets","width":35,"height":29,"scales":[1],"files":["C:\\Users\\alejo\\Desktop\\SportsMatch\\sportsmatch\\client\\assets\\vector-27.png"],"hash":"69ecc6e9be57a6822ffb7a70ff5aa108","name":"vector-27","type":"png","fileHashes":["69ecc6e9be57a6822ffb7a70ff5aa108"]},"98146ef2f1e7e3be9653c0cac9ca2045":{"__packager_asset":true,"fileSystemLocation":"C:\\Users\\alejo\\Desktop\\SportsMatch\\sportsmatch\\client\\assets","httpServerLocation":"/assets/assets","width":78,"height":52,"scales":[1],"files":["C:\\Users\\alejo\\Desktop\\SportsMatch\\sportsmatch\\client\\assets\\group-5361.png"],"hash":"98146ef2f1e7e3be9653c0cac9ca2045","name":"group-5361","type":"png","fileHashes":["98146ef2f1e7e3be9653c0cac9ca2045"]},"ccc38b20fd627277df163aa52df0e010":{"__packager_asset":true,"fileSystemLocation":"C:\\Users\\alejo\\Desktop\\SportsMatch\\sportsmatch\\client\\assets","httpServerLocation":"/assets/assets","width":82,"height":63,"scales":[1],"files":["C:\\Users\\alejo\\Desktop\\SportsMatch\\sportsmatch\\client\\assets\\group13.png"],"hash":"ccc38b20fd627277df163aa52df0e010","name":"group13","type":"png","fileHashes":["ccc38b20fd627277df163aa52df0e010"]},"96ae9a15dfd221b7819f0f454e46b48b":{"__packager_asset":true,"fileSystemLocation":"C:\\Users\\alejo\\Desktop\\SportsMatch\\sportsmatch\\client\\assets","httpServerLocation":"/assets/assets","width":499,"height":720,"scales":[1],"files":["C:\\Users\\alejo\\Desktop\\SportsMatch\\sportsmatch\\client\\assets\\grafico-terreno-juego.png"],"hash":"96ae9a15dfd221b7819f0f454e46b48b","name":"grafico-terreno-juego","type":"png","fileHashes":["96ae9a15dfd221b7819f0f454e46b48b"]},"6f0fbd552721f93dcadaf82ea48b90ce":{"__packager_asset":true,"fileSystemLocation":"C:\\Users\\alejo\\Desktop\\SportsMatch\\sportsmatch\\client\\assets","httpServerLocation":"/assets/assets","width":351,"height":438,"scales":[1],"files":["C:\\Users\\alejo\\Desktop\\SportsMatch\\sportsmatch\\client\\assets\\basketball-jed-villejo-11.png"],"hash":"6f0fbd552721f93dcadaf82ea48b90ce","name":"basketball-jed-villejo-11","type":"png","fileHashes":["6f0fbd552721f93dcadaf82ea48b90ce"]},"00e5229dd1098bf6a948e04048585d66":{"__packager_asset":true,"fileSystemLocation":"C:\\Users\\alejo\\Desktop\\SportsMatch\\sportsmatch\\client\\assets","httpServerLocation":"/assets/assets","width":351,"height":438,"scales":[1],"files":["C:\\Users\\alejo\\Desktop\\SportsMatch\\sportsmatch\\client\\assets\\basketball-unsplash-11.png"],"hash":"00e5229dd1098bf6a948e04048585d66","name":"basketball-unsplash-11","type":"png","fileHashes":["00e5229dd1098bf6a948e04048585d66"]},"26069204d18f8dca80e65d8f6327d746":{"__packager_asset":true,"fileSystemLocation":"C:\\Users\\alejo\\Desktop\\SportsMatch\\sportsmatch\\client\\assets","httpServerLocation":"/assets/assets","width":351,"height":438,"scales":[1],"files":["C:\\Users\\alejo\\Desktop\\SportsMatch\\sportsmatch\\client\\assets\\basketball-unsplash-3-11.png"],"hash":"26069204d18f8dca80e65d8f6327d746","name":"basketball-unsplash-3-11","type":"png","fileHashes":["26069204d18f8dca80e65d8f6327d746"]},"e88f4136a335e4c492d06a0c280579cd":{"__packager_asset":true,"fileSystemLocation":"C:\\Users\\alejo\\Desktop\\SportsMatch\\sportsmatch\\client\\assets","httpServerLocation":"/assets/assets","width":351,"height":438,"scales":[1],"files":["C:\\Users\\alejo\\Desktop\\SportsMatch\\sportsmatch\\client\\assets\\basketball-tim-mossholder-11.png"],"hash":"e88f4136a335e4c492d06a0c280579cd","name":"basketball-tim-mossholder-11","type":"png","fileHashes":["e88f4136a335e4c492d06a0c280579cd"]},"31b0028b96c4a11793f1878c9bcc7fed":{"__packager_asset":true,"fileSystemLocation":"C:\\Users\\alejo\\Desktop\\SportsMatch\\sportsmatch\\client\\assets","httpServerLocation":"/assets/assets","width":351,"height":438,"scales":[1],"files":["C:\\Users\\alejo\\Desktop\\SportsMatch\\sportsmatch\\client\\assets\\basketball-mira-kireeva-11.png"],"hash":"31b0028b96c4a11793f1878c9bcc7fed","name":"basketball-mira-kireeva-11","type":"png","fileHashes":["31b0028b96c4a11793f1878c9bcc7fed"]},"e2158645b3ccdd4deead108c25fdd581":{"__packager_asset":true,"fileSystemLocation":"C:\\Users\\alejo\\Desktop\\SportsMatch\\sportsmatch\\client\\assets","httpServerLocation":"/assets/assets","width":351,"height":438,"scales":[1],"files":["C:\\Users\\alejo\\Desktop\\SportsMatch\\sportsmatch\\client\\assets\\basketball-mira-kireeva-1-11.png"],"hash":"e2158645b3ccdd4deead108c25fdd581","name":"basketball-mira-kireeva-1-11","type":"png","fileHashes":["e2158645b3ccdd4deead108c25fdd581"]},"2d187522b2605df2a39ab9d35942e00f":{"__packager_asset":true,"fileSystemLocation":"C:\\Users\\alejo\\Desktop\\SportsMatch\\sportsmatch\\client\\assets","httpServerLocation":"/assets/assets","width":27,"height":46,"scales":[1],"files":["C:\\Users\\alejo\\Desktop\\SportsMatch\\sportsmatch\\client\\assets\\flecha3.png"],"hash":"2d187522b2605df2a39ab9d35942e00f","name":"flecha3","type":"png","fileHashes":["2d187522b2605df2a39ab9d35942e00f"]},"f4642a4de4fdcf2c1d3f8623a59c253e":{"__packager_asset":true,"fileSystemLocation":"C:\\Users\\alejo\\Desktop\\SportsMatch\\sportsmatch\\client\\assets","httpServerLocation":"/assets/assets","width":91,"height":90,"scales":[1],"files":["C:\\Users\\alejo\\Desktop\\SportsMatch\\sportsmatch\\client\\assets\\ellipse-764.png"],"hash":"f4642a4de4fdcf2c1d3f8623a59c253e","name":"ellipse-764","type":"png","fileHashes":["f4642a4de4fdcf2c1d3f8623a59c253e"]},"fee660cc15a860895e2543511c6ce39f":{"__packager_asset":true,"fileSystemLocation":"C:\\Users\\alejo\\Desktop\\SportsMatch\\sportsmatch\\client\\assets","httpServerLocation":"/assets/assets","width":71,"height":66,"scales":[1],"files":["C:\\Users\\alejo\\Desktop\\SportsMatch\\sportsmatch\\client\\assets\\logo-uem21removebgpreview-15.png"],"hash":"fee660cc15a860895e2543511c6ce39f","name":"logo-uem21removebgpreview-15","type":"png","fileHashes":["fee660cc15a860895e2543511c6ce39f"]},"57ec4552dfdcd176997c6246e834978e":{"__packager_asset":true,"fileSystemLocation":"C:\\Users\\alejo\\Desktop\\SportsMatch\\sportsmatch\\client\\assets","httpServerLocation":"/assets/assets","width":16,"height":70,"scales":[1],"files":["C:\\Users\\alejo\\Desktop\\SportsMatch\\sportsmatch\\client\\assets\\menu-lateral-posterior.png"],"hash":"57ec4552dfdcd176997c6246e834978e","name":"menu-lateral-posterior","type":"png","fileHashes":["57ec4552dfdcd176997c6246e834978e"]},"d9ded4a7f2186605ae8b39f187316353":{"__packager_asset":true,"fileSystemLocation":"C:\\Users\\alejo\\Desktop\\SportsMatch\\sportsmatch\\client\\assets","httpServerLocation":"/assets/assets","width":37,"height":28,"scales":[1],"files":["C:\\Users\\alejo\\Desktop\\SportsMatch\\sportsmatch\\client\\assets\\tics.png"],"hash":"d9ded4a7f2186605ae8b39f187316353","name":"tics","type":"png","fileHashes":["d9ded4a7f2186605ae8b39f187316353"]},"525d4efc2495a5c24e60a6d24676bb2b":{"__packager_asset":true,"fileSystemLocation":"C:\\Users\\alejo\\Desktop\\SportsMatch\\sportsmatch\\client\\assets","httpServerLocation":"/assets/assets","width":37,"height":28,"scales":[1],"files":["C:\\Users\\alejo\\Desktop\\SportsMatch\\sportsmatch\\client\\assets\\group-454.png"],"hash":"525d4efc2495a5c24e60a6d24676bb2b","name":"group-454","type":"png","fileHashes":["525d4efc2495a5c24e60a6d24676bb2b"]},"2ea71dd081a735de3b4268138c69fb20":{"__packager_asset":true,"fileSystemLocation":"C:\\Users\\alejo\\Desktop\\SportsMatch\\sportsmatch\\client\\assets","httpServerLocation":"/assets/assets","width":37,"height":28,"scales":[1],"files":["C:\\Users\\alejo\\Desktop\\SportsMatch\\sportsmatch\\client\\assets\\tics1.png"],"hash":"2ea71dd081a735de3b4268138c69fb20","name":"tics1","type":"png","fileHashes":["2ea71dd081a735de3b4268138c69fb20"]},"1019dccc8254d50c402b460e66d3d482":{"__packager_asset":true,"fileSystemLocation":"C:\\Users\\alejo\\Desktop\\SportsMatch\\sportsmatch\\client\\assets","httpServerLocation":"/assets/assets","width":102,"height":69,"scales":[1],"files":["C:\\Users\\alejo\\Desktop\\SportsMatch\\sportsmatch\\client\\assets\\group-5394.png"],"hash":"1019dccc8254d50c402b460e66d3d482","name":"group-5394","type":"png","fileHashes":["1019dccc8254d50c402b460e66d3d482"]},"81c949c27c9d351ce594c9533837e054":{"__packager_asset":true,"fileSystemLocation":"C:\\Users\\alejo\\Desktop\\SportsMatch\\sportsmatch\\client\\assets","httpServerLocation":"/assets/assets","width":560,"height":132,"scales":[1],"files":["C:\\Users\\alejo\\Desktop\\SportsMatch\\sportsmatch\\client\\assets\\logo3.png"],"hash":"81c949c27c9d351ce594c9533837e054","name":"logo3","type":"png","fileHashes":["81c949c27c9d351ce594c9533837e054"]},"29e2307132aa7e8863e568200532b15b":{"__packager_asset":true,"fileSystemLocation":"C:\\Users\\alejo\\Desktop\\SportsMatch\\sportsmatch\\client\\assets","httpServerLocation":"/assets/assets","width":94,"height":94,"scales":[1],"files":["C:\\Users\\alejo\\Desktop\\SportsMatch\\sportsmatch\\client\\assets\\group-6583.png"],"hash":"29e2307132aa7e8863e568200532b15b","name":"group-6583","type":"png","fileHashes":["29e2307132aa7e8863e568200532b15b"]},"f1a996d91c8d5ce2508009ed1b1b32e6":{"__packager_asset":true,"fileSystemLocation":"C:\\Users\\alejo\\Desktop\\SportsMatch\\sportsmatch\\client\\assets","httpServerLocation":"/assets/assets","width":101,"height":78,"scales":[1],"files":["C:\\Users\\alejo\\Desktop\\SportsMatch\\sportsmatch\\client\\assets\\group10.png"],"hash":"f1a996d91c8d5ce2508009ed1b1b32e6","name":"group10","type":"png","fileHashes":["f1a996d91c8d5ce2508009ed1b1b32e6"]},"3b76bedee1e32f36e4528bd8f159e669":{"__packager_asset":true,"fileSystemLocation":"C:\\Users\\alejo\\Desktop\\SportsMatch\\sportsmatch\\client\\assets","httpServerLocation":"/assets/assets","width":15,"height":63,"scales":[1],"files":["C:\\Users\\alejo\\Desktop\\SportsMatch\\sportsmatch\\client\\assets\\frame-957.png"],"hash":"3b76bedee1e32f36e4528bd8f159e669","name":"frame-957","type":"png","fileHashes":["3b76bedee1e32f36e4528bd8f159e669"]},"9fa767131b6d7b73d00290fe715fe461":{"__packager_asset":true,"fileSystemLocation":"C:\\Users\\alejo\\Desktop\\SportsMatch\\sportsmatch\\client\\assets","httpServerLocation":"/assets/assets","width":136,"height":135,"scales":[1],"files":["C:\\Users\\alejo\\Desktop\\SportsMatch\\sportsmatch\\client\\assets\\mask-group13.png"],"hash":"9fa767131b6d7b73d00290fe715fe461","name":"mask-group13","type":"png","fileHashes":["9fa767131b6d7b73d00290fe715fe461"]},"6baeca785622c99b681526cfebfbb462":{"__packager_asset":true,"fileSystemLocation":"C:\\Users\\alejo\\Desktop\\SportsMatch\\sportsmatch\\client\\assets","httpServerLocation":"/assets/assets","width":57,"height":57,"scales":[1],"files":["C:\\Users\\alejo\\Desktop\\SportsMatch\\sportsmatch\\client\\assets\\image-borroso.png"],"hash":"6baeca785622c99b681526cfebfbb462","name":"image-borroso","type":"png","fileHashes":["6baeca785622c99b681526cfebfbb462"]},"64176e86e452788e23ce6c44310ee0be":{"__packager_asset":true,"fileSystemLocation":"C:\\Users\\alejo\\Desktop\\SportsMatch\\sportsmatch\\client\\assets","httpServerLocation":"/assets/assets","width":83,"height":63,"scales":[1],"files":["C:\\Users\\alejo\\Desktop\\SportsMatch\\sportsmatch\\client\\assets\\group9.png"],"hash":"64176e86e452788e23ce6c44310ee0be","name":"group9","type":"png","fileHashes":["64176e86e452788e23ce6c44310ee0be"]},"b01e805e77c96aa266e734c7bf74bc02":{"__packager_asset":true,"fileSystemLocation":"C:\\Users\\alejo\\Desktop\\SportsMatch\\sportsmatch\\client\\assets","httpServerLocation":"/assets/assets","width":103,"height":38,"scales":[1],"files":["C:\\Users\\alejo\\Desktop\\SportsMatch\\sportsmatch\\client\\assets\\matchButton.png"],"hash":"b01e805e77c96aa266e734c7bf74bc02","name":"matchButton","type":"png","fileHashes":["b01e805e77c96aa266e734c7bf74bc02"]},"5030d2becfbbe795df1102905462f2db":{"__packager_asset":true,"fileSystemLocation":"C:\\Users\\alejo\\Desktop\\SportsMatch\\sportsmatch\\client\\assets","httpServerLocation":"/assets/assets","width":46,"height":45,"scales":[1],"files":["C:\\Users\\alejo\\Desktop\\SportsMatch\\sportsmatch\\client\\assets\\blurryProfile2.png"],"hash":"5030d2becfbbe795df1102905462f2db","name":"blurryProfile2","type":"png","fileHashes":["5030d2becfbbe795df1102905462f2db"]},"0dcebc7ead0bd808997ef6e5471d1a2b":{"__packager_asset":true,"fileSystemLocation":"C:\\Users\\alejo\\Desktop\\SportsMatch\\sportsmatch\\client\\assets","httpServerLocation":"/assets/assets","width":46,"height":45,"scales":[1],"files":["C:\\Users\\alejo\\Desktop\\SportsMatch\\sportsmatch\\client\\assets\\blurryProfile.png"],"hash":"0dcebc7ead0bd808997ef6e5471d1a2b","name":"blurryProfile","type":"png","fileHashes":["0dcebc7ead0bd808997ef6e5471d1a2b"]},"c59f3772ca8f69d377cdf73e71a123e5":{"__packager_asset":true,"fileSystemLocation":"C:\\Users\\alejo\\Desktop\\SportsMatch\\sportsmatch\\client\\assets","httpServerLocation":"/assets/assets","width":138,"height":138,"scales":[1],"files":["C:\\Users\\alejo\\Desktop\\SportsMatch\\sportsmatch\\client\\assets\\simbolo.png"],"hash":"c59f3772ca8f69d377cdf73e71a123e5","name":"simbolo","type":"png","fileHashes":["c59f3772ca8f69d377cdf73e71a123e5"]},"f78bcbd4c991216c47043ffd6ff942fd":{"__packager_asset":true,"fileSystemLocation":"C:\\Users\\alejo\\Desktop\\SportsMatch\\sportsmatch\\client\\assets","httpServerLocation":"/assets/assets","width":162,"height":12,"scales":[1],"files":["C:\\Users\\alejo\\Desktop\\SportsMatch\\sportsmatch\\client\\assets\\line-66.png"],"hash":"f78bcbd4c991216c47043ffd6ff942fd","name":"line-66","type":"png","fileHashes":["f78bcbd4c991216c47043ffd6ff942fd"]},"9f0b25b4b8544d88eba7c47a3b6a661b":{"__packager_asset":true,"fileSystemLocation":"C:\\Users\\alejo\\Desktop\\SportsMatch\\sportsmatch\\client\\assets","httpServerLocation":"/assets/assets","width":36,"height":22,"scales":[1],"files":["C:\\Users\\alejo\\Desktop\\SportsMatch\\sportsmatch\\client\\assets\\coolicon5.png"],"hash":"9f0b25b4b8544d88eba7c47a3b6a661b","name":"coolicon5","type":"png","fileHashes":["9f0b25b4b8544d88eba7c47a3b6a661b"]},"46eaada6f07369e044337f1c83c0bcc5":{"__packager_asset":true,"fileSystemLocation":"C:\\Users\\alejo\\Desktop\\SportsMatch\\sportsmatch\\client\\assets","httpServerLocation":"/assets/assets","width":329,"height":243,"scales":[1],"files":["C:\\Users\\alejo\\Desktop\\SportsMatch\\sportsmatch\\client\\assets\\lineas.png"],"hash":"46eaada6f07369e044337f1c83c0bcc5","name":"lineas","type":"png","fileHashes":["46eaada6f07369e044337f1c83c0bcc5"]},"ab35ccdedb48d7d6e3f66c416be8a8bf":{"__packager_asset":true,"fileSystemLocation":"C:\\Users\\alejo\\Desktop\\SportsMatch\\sportsmatch\\client\\assets","httpServerLocation":"/assets/assets","width":894,"height":212,"scales":[1],"files":["C:\\Users\\alejo\\Desktop\\SportsMatch\\sportsmatch\\client\\assets\\logotipo.png"],"hash":"ab35ccdedb48d7d6e3f66c416be8a8bf","name":"logotipo","type":"png","fileHashes":["ab35ccdedb48d7d6e3f66c416be8a8bf"]},"1046450968afa3567f8b9e65a6d18b6b":{"__packager_asset":true,"fileSystemLocation":"C:\\Users\\alejo\\Desktop\\SportsMatch\\sportsmatch\\client\\assets","httpServerLocation":"/assets/assets","width":3316,"height":1245,"scales":[1],"files":["C:\\Users\\alejo\\Desktop\\SportsMatch\\sportsmatch\\client\\assets\\liniasimagen.png"],"hash":"1046450968afa3567f8b9e65a6d18b6b","name":"liniasimagen","type":"png","fileHashes":["1046450968afa3567f8b9e65a6d18b6b"]},"56f9869814b6ec3ad58a71be330f596f":{"__packager_asset":true,"fileSystemLocation":"C:\\Users\\alejo\\Desktop\\SportsMatch\\sportsmatch\\client\\assets","httpServerLocation":"/assets/assets","width":3316,"height":1245,"scales":[1],"files":["C:\\Users\\alejo\\Desktop\\SportsMatch\\sportsmatch\\client\\assets\\fondo1.png"],"hash":"56f9869814b6ec3ad58a71be330f596f","name":"fondo1","type":"png","fileHashes":["56f9869814b6ec3ad58a71be330f596f"]},"175431aa0466f6190fe4f65bcc345dbb":{"__packager_asset":true,"fileSystemLocation":"C:\\Users\\alejo\\Desktop\\SportsMatch\\sportsmatch\\client\\assets","httpServerLocation":"/assets/assets","width":65,"height":48,"scales":[1],"files":["C:\\Users\\alejo\\Desktop\\SportsMatch\\sportsmatch\\client\\assets\\vector4.png"],"hash":"175431aa0466f6190fe4f65bcc345dbb","name":"vector4","type":"png","fileHashes":["175431aa0466f6190fe4f65bcc345dbb"]},"5822e84c90a2daea09baeb90c5311521":{"__packager_asset":true,"fileSystemLocation":"C:\\Users\\alejo\\Desktop\\SportsMatch\\sportsmatch\\client\\assets","httpServerLocation":"/assets/assets","width":44,"height":54,"scales":[1],"files":["C:\\Users\\alejo\\Desktop\\SportsMatch\\sportsmatch\\client\\assets\\simbolo3.png"],"hash":"5822e84c90a2daea09baeb90c5311521","name":"simbolo3","type":"png","fileHashes":["5822e84c90a2daea09baeb90c5311521"]},"910df1b864a696e32bda56876ddf61cd":{"__packager_asset":true,"fileSystemLocation":"C:\\Users\\alejo\\Desktop\\SportsMatch\\sportsmatch\\client\\node_modules\\react-native-check-box\\img","httpServerLocation":"/assets/node_modules/react-native-check-box/img","width":24,"height":24,"scales":[1],"files":["C:\\Users\\alejo\\Desktop\\SportsMatch\\sportsmatch\\client\\node_modules\\react-native-check-box\\img\\ic_indeterminate_check_box.png"],"hash":"910df1b864a696e32bda56876ddf61cd","name":"ic_indeterminate_check_box","type":"png","fileHashes":["910df1b864a696e32bda56876ddf61cd"]},"5d3b135d5214e780d63b968d2ade7240":{"__packager_asset":true,"fileSystemLocation":"C:\\Users\\alejo\\Desktop\\SportsMatch\\sportsmatch\\client\\node_modules\\react-native-check-box\\img","httpServerLocation":"/assets/node_modules/react-native-check-box/img","width":24,"height":24,"scales":[1,2,3],"files":["C:\\Users\\alejo\\Desktop\\SportsMatch\\sportsmatch\\client\\node_modules\\react-native-check-box\\img\\ic_check_box.png","C:\\Users\\alejo\\Desktop\\SportsMatch\\sportsmatch\\client\\node_modules\\react-native-check-box\\img\\ic_check_box@2x.png","C:\\Users\\alejo\\Desktop\\SportsMatch\\sportsmatch\\client\\node_modules\\react-native-check-box\\img\\ic_check_box@3x.png"],"hash":"5d3b135d5214e780d63b968d2ade7240","name":"ic_check_box","type":"png","fileHashes":["5326847c48dd354f9aff1535c8737c47","052bc0acdb0d803974303036ff8400d0","e134ddab19b3be7a4d31aa4a53045330"]},"a254967b747795d2bc7217850e45291a":{"__packager_asset":true,"fileSystemLocation":"C:\\Users\\alejo\\Desktop\\SportsMatch\\sportsmatch\\client\\node_modules\\react-native-check-box\\img","httpServerLocation":"/assets/node_modules/react-native-check-box/img","width":24,"height":24,"scales":[1,2,3],"files":["C:\\Users\\alejo\\Desktop\\SportsMatch\\sportsmatch\\client\\node_modules\\react-native-check-box\\img\\ic_check_box_outline_blank.png","C:\\Users\\alejo\\Desktop\\SportsMatch\\sportsmatch\\client\\node_modules\\react-native-check-box\\img\\ic_check_box_outline_blank@2x.png","C:\\Users\\alejo\\Desktop\\SportsMatch\\sportsmatch\\client\\node_modules\\react-native-check-box\\img\\ic_check_box_outline_blank@3x.png"],"hash":"a254967b747795d2bc7217850e45291a","name":"ic_check_box_outline_blank","type":"png","fileHashes":["41e56027aa51fda1eef209fa6382f074","e96f481e68c7f83be9a88dd5f35bd0d0","9ce6a2b31ec720826df2300e6ecaf594"]},"335607015e1ed20e89203f03959c16fe":{"__packager_asset":true,"fileSystemLocation":"C:\\Users\\alejo\\Desktop\\SportsMatch\\sportsmatch\\client\\assets","httpServerLocation":"/assets/assets","width":3316,"height":1274,"scales":[1],"files":["C:\\Users\\alejo\\Desktop\\SportsMatch\\sportsmatch\\client\\assets\\fondo2.png"],"hash":"335607015e1ed20e89203f03959c16fe","name":"fondo2","type":"png","fileHashes":["335607015e1ed20e89203f03959c16fe"]},"a576781c3dd19c60241320a8c872e3e4":{"__packager_asset":true,"fileSystemLocation":"C:\\Users\\alejo\\Desktop\\SportsMatch\\sportsmatch\\client\\assets","httpServerLocation":"/assets/assets","width":61,"height":63,"scales":[1],"files":["C:\\Users\\alejo\\Desktop\\SportsMatch\\sportsmatch\\client\\assets\\simbolo4.png"],"hash":"a576781c3dd19c60241320a8c872e3e4","name":"simbolo4","type":"png","fileHashes":["a576781c3dd19c60241320a8c872e3e4"]},"8eb26994ad1610bdf5babc39ec0679be":{"__packager_asset":true,"fileSystemLocation":"C:\\Users\\alejo\\Desktop\\SportsMatch\\sportsmatch\\client\\assets","httpServerLocation":"/assets/assets","width":135,"height":135,"scales":[1],"files":["C:\\Users\\alejo\\Desktop\\SportsMatch\\sportsmatch\\client\\assets\\avatar.png"],"hash":"8eb26994ad1610bdf5babc39ec0679be","name":"avatar","type":"png","fileHashes":["8eb26994ad1610bdf5babc39ec0679be"]},"661db817565a804bb52edc062d0eca84":{"__packager_asset":true,"fileSystemLocation":"C:\\Users\\alejo\\Desktop\\SportsMatch\\sportsmatch\\client\\assets","httpServerLocation":"/assets/assets","width":40,"height":45,"scales":[1],"files":["C:\\Users\\alejo\\Desktop\\SportsMatch\\sportsmatch\\client\\assets\\pictograma1.png"],"hash":"661db817565a804bb52edc062d0eca84","name":"pictograma1","type":"png","fileHashes":["661db817565a804bb52edc062d0eca84"]},"519bfe32d354a98f5bacc18dd121d5e0":{"__packager_asset":true,"fileSystemLocation":"C:\\Users\\alejo\\Desktop\\SportsMatch\\sportsmatch\\client\\assets","httpServerLocation":"/assets/assets","width":63,"height":50,"scales":[1],"files":["C:\\Users\\alejo\\Desktop\\SportsMatch\\sportsmatch\\client\\assets\\contact.png"],"hash":"519bfe32d354a98f5bacc18dd121d5e0","name":"contact","type":"png","fileHashes":["519bfe32d354a98f5bacc18dd121d5e0"]},"829408de88d7b918003ed02410e68cf4":{"__packager_asset":true,"fileSystemLocation":"C:\\Users\\alejo\\Desktop\\SportsMatch\\sportsmatch\\client\\assets","httpServerLocation":"/assets/assets","width":128,"height":128,"scales":[1],"files":["C:\\Users\\alejo\\Desktop\\SportsMatch\\sportsmatch\\client\\assets\\readed.png"],"hash":"829408de88d7b918003ed02410e68cf4","name":"readed","type":"png","fileHashes":["829408de88d7b918003ed02410e68cf4"]},"d9042ee65cacd47e2203cf488137c608":{"__packager_asset":true,"fileSystemLocation":"C:\\Users\\alejo\\Desktop\\SportsMatch\\sportsmatch\\client\\assets","httpServerLocation":"/assets/assets","width":128,"height":128,"scales":[1],"files":["C:\\Users\\alejo\\Desktop\\SportsMatch\\sportsmatch\\client\\assets\\notReaded.png"],"hash":"d9042ee65cacd47e2203cf488137c608","name":"notReaded","type":"png","fileHashes":["d9042ee65cacd47e2203cf488137c608"]},"ace097e5817555658c91cd745c577f24":{"__packager_asset":true,"fileSystemLocation":"C:\\Users\\alejo\\Desktop\\SportsMatch\\sportsmatch\\client\\assets","httpServerLocation":"/assets/assets","width":45,"height":45,"scales":[1],"files":["C:\\Users\\alejo\\Desktop\\SportsMatch\\sportsmatch\\client\\assets\\group-565.png"],"hash":"ace097e5817555658c91cd745c577f24","name":"group-565","type":"png","fileHashes":["ace097e5817555658c91cd745c577f24"]},"64647d938aa324429b375b58f7233733":{"__packager_asset":true,"fileSystemLocation":"C:\\Users\\alejo\\Desktop\\SportsMatch\\sportsmatch\\client\\assets","httpServerLocation":"/assets/assets","width":2868,"height":2868,"scales":[1],"files":["C:\\Users\\alejo\\Desktop\\SportsMatch\\sportsmatch\\client\\assets\\imagen-de-fondo3.png"],"hash":"64647d938aa324429b375b58f7233733","name":"imagen-de-fondo3","type":"png","fileHashes":["64647d938aa324429b375b58f7233733"]},"5648b736dfe11a87b3de82871308b617":{"__packager_asset":true,"fileSystemLocation":"C:\\Users\\alejo\\Desktop\\SportsMatch\\sportsmatch\\client\\assets","httpServerLocation":"/assets/assets","width":27,"height":46,"scales":[1],"files":["C:\\Users\\alejo\\Desktop\\SportsMatch\\sportsmatch\\client\\assets\\coolicon1.png"],"hash":"5648b736dfe11a87b3de82871308b617","name":"coolicon1","type":"png","fileHashes":["5648b736dfe11a87b3de82871308b617"]},"791a8b2b017f5ef703c39072a14c4fae":{"__packager_asset":true,"fileSystemLocation":"C:\\Users\\alejo\\Desktop\\SportsMatch\\sportsmatch\\client\\assets","httpServerLocation":"/assets/assets","width":93,"height":92,"scales":[1],"files":["C:\\Users\\alejo\\Desktop\\SportsMatch\\sportsmatch\\client\\assets\\simbolo6.png"],"hash":"791a8b2b017f5ef703c39072a14c4fae","name":"simbolo6","type":"png","fileHashes":["791a8b2b017f5ef703c39072a14c4fae"]},"818ae4b3f2d33ea4752411a38cc42425":{"__packager_asset":true,"fileSystemLocation":"C:\\Users\\alejo\\Desktop\\SportsMatch\\sportsmatch\\client\\assets","httpServerLocation":"/assets/assets","width":71,"height":93,"scales":[1],"files":["C:\\Users\\alejo\\Desktop\\SportsMatch\\sportsmatch\\client\\assets\\simbolo7.png"],"hash":"818ae4b3f2d33ea4752411a38cc42425","name":"simbolo7","type":"png","fileHashes":["818ae4b3f2d33ea4752411a38cc42425"]},"bc30ec98db5cc24fb438bfde3fe24f4c":{"__packager_asset":true,"fileSystemLocation":"C:\\Users\\alejo\\Desktop\\SportsMatch\\sportsmatch\\client\\assets","httpServerLocation":"/assets/assets","width":11468,"height":2988,"scales":[1],"files":["C:\\Users\\alejo\\Desktop\\SportsMatch\\sportsmatch\\client\\assets\\group-2412.png"],"hash":"bc30ec98db5cc24fb438bfde3fe24f4c","name":"group-2412","type":"png","fileHashes":["bc30ec98db5cc24fb438bfde3fe24f4c"]},"5a0e8404f7c1ecb97bc76994308cbaf4":{"__packager_asset":true,"fileSystemLocation":"C:\\Users\\alejo\\Desktop\\SportsMatch\\sportsmatch\\client\\assets","httpServerLocation":"/assets/assets","width":27,"height":45,"scales":[1],"files":["C:\\Users\\alejo\\Desktop\\SportsMatch\\sportsmatch\\client\\assets\\coolicon.png"],"hash":"5a0e8404f7c1ecb97bc76994308cbaf4","name":"coolicon","type":"png","fileHashes":["5a0e8404f7c1ecb97bc76994308cbaf4"]},"c90fb4585dd852a3d67af39baf923f67":{"__packager_asset":true,"fileSystemLocation":"C:\\Users\\alejo\\Desktop\\SportsMatch\\sportsmatch\\client\\node_modules\\@react-navigation\\elements\\src\\assets","httpServerLocation":"/assets/node_modules/@react-navigation/elements/src/assets","width":12,"height":21,"scales":[1,1.5,2,3,4],"files":["C:\\Users\\alejo\\Desktop\\SportsMatch\\sportsmatch\\client\\node_modules\\@react-navigation\\elements\\src\\assets\\back-icon@1x.ios.png","C:\\Users\\alejo\\Desktop\\SportsMatch\\sportsmatch\\client\\node_modules\\@react-navigation\\elements\\src\\assets\\back-icon@1.5x.ios.png","C:\\Users\\alejo\\Desktop\\SportsMatch\\sportsmatch\\client\\node_modules\\@react-navigation\\elements\\src\\assets\\back-icon@2x.ios.png","C:\\Users\\alejo\\Desktop\\SportsMatch\\sportsmatch\\client\\node_modules\\@react-navigation\\elements\\src\\assets\\back-icon@3x.ios.png","C:\\Users\\alejo\\Desktop\\SportsMatch\\sportsmatch\\client\\node_modules\\@react-navigation\\elements\\src\\assets\\back-icon@4x.ios.png"],"hash":"c90fb4585dd852a3d67af39baf923f67","name":"back-icon","type":"png","fileHashes":["7d40544b395c5949f4646f5e150fe020","cdd04e13d4ec83ff0cd13ec8dabdc341","a132ecc4ba5c1517ff83c0fb321bc7fc","0ea69b5077e7c4696db85dbcba75b0e1","f5b790e2ac193b3d41015edb3551f9b8"]},"5223c8d9b0d08b82a5670fb5f71faf78":{"__packager_asset":true,"fileSystemLocation":"C:\\Users\\alejo\\Desktop\\SportsMatch\\sportsmatch\\client\\node_modules\\@react-navigation\\elements\\src\\assets","httpServerLocation":"/assets/node_modules/@react-navigation/elements/src/assets","width":50,"height":85,"scales":[1],"files":["C:\\Users\\alejo\\Desktop\\SportsMatch\\sportsmatch\\client\\node_modules\\@react-navigation\\elements\\src\\assets\\back-icon-mask.png"],"hash":"5223c8d9b0d08b82a5670fb5f71faf78","name":"back-icon-mask","type":"png","fileHashes":["5223c8d9b0d08b82a5670fb5f71faf78"]},"293cc82521cf9a2716e5b21c4a6dd00e":{"__packager_asset":true,"fileSystemLocation":"C:\\Users\\alejo\\Desktop\\SportsMatch\\sportsmatch\\client\\assets","httpServerLocation":"/assets/assets","width":270,"height":261,"scales":[1],"files":["C:\\Users\\alejo\\Desktop\\SportsMatch\\sportsmatch\\client\\assets\\basketball-unsplash-3-1.png"],"hash":"293cc82521cf9a2716e5b21c4a6dd00e","name":"basketball-unsplash-3-1","type":"png","fileHashes":["293cc82521cf9a2716e5b21c4a6dd00e"]},"c35a5d833fe9bc6cc802a275fd612137":{"__packager_asset":true,"fileSystemLocation":"C:\\Users\\alejo\\Desktop\\SportsMatch\\sportsmatch\\client\\assets\\fonts","httpServerLocation":"/assets/assets/fonts","scales":[1],"files":["C:\\Users\\alejo\\Desktop\\SportsMatch\\sportsmatch\\client\\assets\\fonts\\OpenSans-SemiBold.ttf"],"hash":"c35a5d833fe9bc6cc802a275fd612137","name":"OpenSans-SemiBold","type":"ttf","fileHashes":["c35a5d833fe9bc6cc802a275fd612137"]},"079af0e2936ccb99b391ddc0bbb73dcb":{"__packager_asset":true,"fileSystemLocation":"C:\\Users\\alejo\\Desktop\\SportsMatch\\sportsmatch\\client\\assets\\fonts","httpServerLocation":"/assets/assets/fonts","scales":[1],"files":["C:\\Users\\alejo\\Desktop\\SportsMatch\\sportsmatch\\client\\assets\\fonts\\Inter-Regular.ttf"],"hash":"079af0e2936ccb99b391ddc0bbb73dcb","name":"Inter-Regular","type":"ttf","fileHashes":["079af0e2936ccb99b391ddc0bbb73dcb"]},"275bfea5dc74c33f51916fee80feae67":{"__packager_asset":true,"fileSystemLocation":"C:\\Users\\alejo\\Desktop\\SportsMatch\\sportsmatch\\client\\assets\\fonts","httpServerLocation":"/assets/assets/fonts","scales":[1],"files":["C:\\Users\\alejo\\Desktop\\SportsMatch\\sportsmatch\\client\\assets\\fonts\\Inter-Bold.ttf"],"hash":"275bfea5dc74c33f51916fee80feae67","name":"Inter-Bold","type":"ttf","fileHashes":["275bfea5dc74c33f51916fee80feae67"]},"a364dc7a784101f7c8f6791c7b4514ce":{"__packager_asset":true,"fileSystemLocation":"C:\\Users\\alejo\\Desktop\\SportsMatch\\sportsmatch\\client\\node_modules\\@react-navigation\\elements\\src\\assets","httpServerLocation":"/assets/node_modules/@react-navigation/elements/src/assets","width":24,"height":24,"scales":[1,1.5,2,3,4],"files":["C:\\Users\\alejo\\Desktop\\SportsMatch\\sportsmatch\\client\\node_modules\\@react-navigation\\elements\\src\\assets\\back-icon@1x.android.png","C:\\Users\\alejo\\Desktop\\SportsMatch\\sportsmatch\\client\\node_modules\\@react-navigation\\elements\\src\\assets\\back-icon@1.5x.android.png","C:\\Users\\alejo\\Desktop\\SportsMatch\\sportsmatch\\client\\node_modules\\@react-navigation\\elements\\src\\assets\\back-icon@2x.android.png","C:\\Users\\alejo\\Desktop\\SportsMatch\\sportsmatch\\client\\node_modules\\@react-navigation\\elements\\src\\assets\\back-icon@3x.android.png","C:\\Users\\alejo\\Desktop\\SportsMatch\\sportsmatch\\client\\node_modules\\@react-navigation\\elements\\src\\assets\\back-icon@4x.android.png"],"hash":"a364dc7a784101f7c8f6791c7b4514ce","name":"back-icon","type":"png","fileHashes":["778ffc9fe8773a878e9c30a6304784de","376d6a4c7f622917c39feb23671ef71d","c79c3606a1cf168006ad3979763c7e0c","02bc1fa7c0313217bde2d65ccbff40c9","35ba0eaec5a4f5ed12ca16fabeae451d"]}}